{"info":{"year":2024,"version":"1.0","description":"VIA project exported to COCO format using VGG Image Annotator (http://www.robots.ox.ac.uk/~vgg/software/via/)","contributor":"","url":"http://www.robots.ox.ac.uk/~vgg/software/via/","date_created":"Sun Sep 08 2024 20:13:30 GMT+0530 (India Standard Time)"},"images":[{"id":1,"width":203,"height":50,"file_name":"1724218180299.jpeg","license":0,"flickr_url":"C:\\Users\\nikhi\\Pictures\\irctc-captcha\\data\\1724218180299.jpeg","coco_url":"C:\\Users\\nikhi\\Pictures\\irctc-captcha\\data\\1724218180299.jpeg","date_captured":""},{"id":2,"width":203,"height":50,"file_name":"1724218180400.jpeg","license":0,"flickr_url":"C:\\Users\\nikhi\\Pictures\\irctc-captcha\\data\\1724218180400.jpeg","coco_url":"C:\\Users\\nikhi\\Pictures\\irctc-captcha\\data\\1724218180400.jpeg","date_captured":""},{"id":3,"width":203,"height":50,"file_name":"1724218180510.jpeg","license":0,"flickr_url":"C:\\Users\\nikhi\\Pictures\\irctc-captcha\\data\\1724218180510.jpeg","coco_url":"C:\\Users\\nikhi\\Pictures\\irctc-captcha\\data\\1724218180510.jpeg","date_captured":""},{"id":4,"width":203,"height":50,"file_name":"1724218180678.jpeg","license":0,"flickr_url":"C:\\Users\\nikhi\\Pictures\\irctc-captcha\\data\\1724218180678.jpeg","coco_url":"C:\\Users\\nikhi\\Pictures\\irctc-captcha\\data\\1724218180678.jpeg","date_captured":""},{"id":5,"width":203,"height":50,"file_name":"1724218180821.jpeg","license":0,"flickr_url":"C:\\Users\\nikhi\\Pictures\\irctc-captcha\\data\\1724218180821.jpeg","coco_url":"C:\\Users\\nikhi\\Pictures\\irctc-captcha\\data\\1724218180821.jpeg","date_captured":""},{"id":6,"width":203,"height":50,"file_name":"1724218180930.jpeg","license":0,"flickr_url":"C:\\Users\\nikhi\\Pictures\\irctc-captcha\\data\\1724218180930.jpeg","coco_url":"C:\\Users\\nikhi\\Pictures\\irctc-captcha\\data\\1724218180930.jpeg","date_captured":""},{"id":7,"width":203,"height":50,"file_name":"1724218181038.jpeg","license":0,"flickr_url":"C:\\Users\\nikhi\\Pictures\\irctc-captcha\\data\\1724218181038.jpeg","coco_url":"C:\\Users\\nikhi\\Pictures\\irctc-captcha\\data\\1724218181038.jpeg","date_captured":""},{"id":8,"width":203,"height":50,"file_name":"1724218181206.jpeg","license":0,"flickr_url":"C:\\Users\\nikhi\\Pictures\\irctc-captcha\\data\\1724218181206.jpeg","coco_url":"C:\\Users\\nikhi\\Pictures\\irctc-captcha\\data\\1724218181206.jpeg","date_captured":""},{"id":9,"width":203,"height":50,"file_name":"1724218181401.jpeg","license":0,"flickr_url":"C:\\Users\\nikhi\\Pictures\\irctc-captcha\\data\\1724218181401.jpeg","coco_url":"C:\\Users\\nikhi\\Pictures\\irctc-captcha\\data\\1724218181401.jpeg","date_captured":""},{"id":10,"width":203,"height":50,"file_name":"1724218181523.jpeg","license":0,"flickr_url":"C:\\Users\\nikhi\\Pictures\\irctc-captcha\\data\\1724218181523.jpeg","coco_url":"C:\\Users\\nikhi\\Pictures\\irctc-captcha\\data\\1724218181523.jpeg","date_captured":""},{"id":11,"width":203,"height":50,"file_name":"1724218181625.jpeg","license":0,"flickr_url":"C:\\Users\\nikhi\\Pictures\\irctc-captcha\\data\\1724218181625.jpeg","coco_url":"C:\\Users\\nikhi\\Pictures\\irctc-captcha\\data\\1724218181625.jpeg","date_captured":""},{"id":12,"width":203,"height":50,"file_name":"1724218181728.jpeg","license":0,"flickr_url":"C:\\Users\\nikhi\\Pictures\\irctc-captcha\\data\\1724218181728.jpeg","coco_url":"C:\\Users\\nikhi\\Pictures\\irctc-captcha\\data\\1724218181728.jpeg","date_captured":""},{"id":13,"width":203,"height":50,"file_name":"1724218181835.jpeg","license":0,"flickr_url":"C:\\Users\\nikhi\\Pictures\\irctc-captcha\\data\\1724218181835.jpeg","coco_url":"C:\\Users\\nikhi\\Pictures\\irctc-captcha\\data\\1724218181835.jpeg","date_captured":""},{"id":14,"width":203,"height":50,"file_name":"1724218181953.jpeg","license":0,"flickr_url":"C:\\Users\\nikhi\\Pictures\\irctc-captcha\\data\\1724218181953.jpeg","coco_url":"C:\\Users\\nikhi\\Pictures\\irctc-captcha\\data\\1724218181953.jpeg","date_captured":""},{"id":15,"width":203,"height":50,"file_name":"1724218182098.jpeg","license":0,"flickr_url":"C:\\Users\\nikhi\\Pictures\\irctc-captcha\\data\\1724218182098.jpeg","coco_url":"C:\\Users\\nikhi\\Pictures\\irctc-captcha\\data\\1724218182098.jpeg","date_captured":""},{"id":16,"width":203,"height":50,"file_name":"1724218182477.jpeg","license":0,"flickr_url":"C:\\Users\\nikhi\\Pictures\\irctc-captcha\\data\\1724218182477.jpeg","coco_url":"C:\\Users\\nikhi\\Pictures\\irctc-captcha\\data\\1724218182477.jpeg","date_captured":""},{"id":17,"width":203,"height":50,"file_name":"1724218182565.jpeg","license":0,"flickr_url":"C:\\Users\\nikhi\\Pictures\\irctc-captcha\\data\\1724218182565.jpeg","coco_url":"C:\\Users\\nikhi\\Pictures\\irctc-captcha\\data\\1724218182565.jpeg","date_captured":""},{"id":18,"width":203,"height":50,"file_name":"1724218182646.jpeg","license":0,"flickr_url":"C:\\Users\\nikhi\\Pictures\\irctc-captcha\\data\\1724218182646.jpeg","coco_url":"C:\\Users\\nikhi\\Pictures\\irctc-captcha\\data\\1724218182646.jpeg","date_captured":""},{"id":19,"width":203,"height":50,"file_name":"1724218182770.jpeg","license":0,"flickr_url":"C:\\Users\\nikhi\\Pictures\\irctc-captcha\\data\\1724218182770.jpeg","coco_url":"C:\\Users\\nikhi\\Pictures\\irctc-captcha\\data\\1724218182770.jpeg","date_captured":""},{"id":20,"width":203,"height":50,"file_name":"1724218182880.jpeg","license":0,"flickr_url":"C:\\Users\\nikhi\\Pictures\\irctc-captcha\\data\\1724218182880.jpeg","coco_url":"C:\\Users\\nikhi\\Pictures\\irctc-captcha\\data\\1724218182880.jpeg","date_captured":""},{"id":21,"width":203,"height":50,"file_name":"1724218183069.jpeg","license":0,"flickr_url":"C:\\Users\\nikhi\\Pictures\\irctc-captcha\\data\\1724218183069.jpeg","coco_url":"C:\\Users\\nikhi\\Pictures\\irctc-captcha\\data\\1724218183069.jpeg","date_captured":""},{"id":22,"width":203,"height":50,"file_name":"1724218183177.jpeg","license":0,"flickr_url":"C:\\Users\\nikhi\\Pictures\\irctc-captcha\\data\\1724218183177.jpeg","coco_url":"C:\\Users\\nikhi\\Pictures\\irctc-captcha\\data\\1724218183177.jpeg","date_captured":""},{"id":23,"width":203,"height":50,"file_name":"1724218183268.jpeg","license":0,"flickr_url":"C:\\Users\\nikhi\\Pictures\\irctc-captcha\\data\\1724218183268.jpeg","coco_url":"C:\\Users\\nikhi\\Pictures\\irctc-captcha\\data\\1724218183268.jpeg","date_captured":""},{"id":24,"width":203,"height":50,"file_name":"1724218183354.jpeg","license":0,"flickr_url":"C:\\Users\\nikhi\\Pictures\\irctc-captcha\\data\\1724218183354.jpeg","coco_url":"C:\\Users\\nikhi\\Pictures\\irctc-captcha\\data\\1724218183354.jpeg","date_captured":""},{"id":25,"width":203,"height":50,"file_name":"1724218183432.jpeg","license":0,"flickr_url":"C:\\Users\\nikhi\\Pictures\\irctc-captcha\\data\\1724218183432.jpeg","coco_url":"C:\\Users\\nikhi\\Pictures\\irctc-captcha\\data\\1724218183432.jpeg","date_captured":""},{"id":26,"width":203,"height":50,"file_name":"1724218183521.jpeg","license":0,"flickr_url":"C:\\Users\\nikhi\\Pictures\\irctc-captcha\\data\\1724218183521.jpeg","coco_url":"C:\\Users\\nikhi\\Pictures\\irctc-captcha\\data\\1724218183521.jpeg","date_captured":""},{"id":27,"width":203,"height":50,"file_name":"1724218183613.jpeg","license":0,"flickr_url":"C:\\Users\\nikhi\\Pictures\\irctc-captcha\\data\\1724218183613.jpeg","coco_url":"C:\\Users\\nikhi\\Pictures\\irctc-captcha\\data\\1724218183613.jpeg","date_captured":""},{"id":28,"width":203,"height":50,"file_name":"1724218183683.jpeg","license":0,"flickr_url":"C:\\Users\\nikhi\\Pictures\\irctc-captcha\\data\\1724218183683.jpeg","coco_url":"C:\\Users\\nikhi\\Pictures\\irctc-captcha\\data\\1724218183683.jpeg","date_captured":""},{"id":29,"width":203,"height":50,"file_name":"1724218183768.jpeg","license":0,"flickr_url":"C:\\Users\\nikhi\\Pictures\\irctc-captcha\\data\\1724218183768.jpeg","coco_url":"C:\\Users\\nikhi\\Pictures\\irctc-captcha\\data\\1724218183768.jpeg","date_captured":""},{"id":30,"width":203,"height":50,"file_name":"1724218183847.jpeg","license":0,"flickr_url":"C:\\Users\\nikhi\\Pictures\\irctc-captcha\\data\\1724218183847.jpeg","coco_url":"C:\\Users\\nikhi\\Pictures\\irctc-captcha\\data\\1724218183847.jpeg","date_captured":""},{"id":31,"width":203,"height":50,"file_name":"1724218184116.jpeg","license":0,"flickr_url":"C:\\Users\\nikhi\\Pictures\\irctc-captcha\\data\\1724218184116.jpeg","coco_url":"C:\\Users\\nikhi\\Pictures\\irctc-captcha\\data\\1724218184116.jpeg","date_captured":""},{"id":32,"width":203,"height":50,"file_name":"1724218184185.jpeg","license":0,"flickr_url":"C:\\Users\\nikhi\\Pictures\\irctc-captcha\\data\\1724218184185.jpeg","coco_url":"C:\\Users\\nikhi\\Pictures\\irctc-captcha\\data\\1724218184185.jpeg","date_captured":""},{"id":33,"width":203,"height":50,"file_name":"1724218184249.jpeg","license":0,"flickr_url":"C:\\Users\\nikhi\\Pictures\\irctc-captcha\\data\\1724218184249.jpeg","coco_url":"C:\\Users\\nikhi\\Pictures\\irctc-captcha\\data\\1724218184249.jpeg","date_captured":""},{"id":34,"width":203,"height":50,"file_name":"1724218184322.jpeg","license":0,"flickr_url":"C:\\Users\\nikhi\\Pictures\\irctc-captcha\\data\\1724218184322.jpeg","coco_url":"C:\\Users\\nikhi\\Pictures\\irctc-captcha\\data\\1724218184322.jpeg","date_captured":""},{"id":35,"width":203,"height":50,"file_name":"1724218184420.jpeg","license":0,"flickr_url":"C:\\Users\\nikhi\\Pictures\\irctc-captcha\\data\\1724218184420.jpeg","coco_url":"C:\\Users\\nikhi\\Pictures\\irctc-captcha\\data\\1724218184420.jpeg","date_captured":""},{"id":36,"width":203,"height":50,"file_name":"1724218184500.jpeg","license":0,"flickr_url":"C:\\Users\\nikhi\\Pictures\\irctc-captcha\\data\\1724218184500.jpeg","coco_url":"C:\\Users\\nikhi\\Pictures\\irctc-captcha\\data\\1724218184500.jpeg","date_captured":""},{"id":37,"width":203,"height":50,"file_name":"1724218184573.jpeg","license":0,"flickr_url":"C:\\Users\\nikhi\\Pictures\\irctc-captcha\\data\\1724218184573.jpeg","coco_url":"C:\\Users\\nikhi\\Pictures\\irctc-captcha\\data\\1724218184573.jpeg","date_captured":""},{"id":38,"width":203,"height":50,"file_name":"1724218184689.jpeg","license":0,"flickr_url":"C:\\Users\\nikhi\\Pictures\\irctc-captcha\\data\\1724218184689.jpeg","coco_url":"C:\\Users\\nikhi\\Pictures\\irctc-captcha\\data\\1724218184689.jpeg","date_captured":""},{"id":39,"width":203,"height":50,"file_name":"1724218184803.jpeg","license":0,"flickr_url":"C:\\Users\\nikhi\\Pictures\\irctc-captcha\\data\\1724218184803.jpeg","coco_url":"C:\\Users\\nikhi\\Pictures\\irctc-captcha\\data\\1724218184803.jpeg","date_captured":""},{"id":40,"width":203,"height":50,"file_name":"1724218184918.jpeg","license":0,"flickr_url":"C:\\Users\\nikhi\\Pictures\\irctc-captcha\\data\\1724218184918.jpeg","coco_url":"C:\\Users\\nikhi\\Pictures\\irctc-captcha\\data\\1724218184918.jpeg","date_captured":""},{"id":41,"width":203,"height":50,"file_name":"1724218185150.jpeg","license":0,"flickr_url":"C:\\Users\\nikhi\\Pictures\\irctc-captcha\\data\\1724218185150.jpeg","coco_url":"C:\\Users\\nikhi\\Pictures\\irctc-captcha\\data\\1724218185150.jpeg","date_captured":""},{"id":42,"width":203,"height":50,"file_name":"1724218185259.jpeg","license":0,"flickr_url":"C:\\Users\\nikhi\\Pictures\\irctc-captcha\\data\\1724218185259.jpeg","coco_url":"C:\\Users\\nikhi\\Pictures\\irctc-captcha\\data\\1724218185259.jpeg","date_captured":""},{"id":43,"width":203,"height":50,"file_name":"1724218185323.jpeg","license":0,"flickr_url":"C:\\Users\\nikhi\\Pictures\\irctc-captcha\\data\\1724218185323.jpeg","coco_url":"C:\\Users\\nikhi\\Pictures\\irctc-captcha\\data\\1724218185323.jpeg","date_captured":""},{"id":44,"width":203,"height":50,"file_name":"1724218185397.jpeg","license":0,"flickr_url":"C:\\Users\\nikhi\\Pictures\\irctc-captcha\\data\\1724218185397.jpeg","coco_url":"C:\\Users\\nikhi\\Pictures\\irctc-captcha\\data\\1724218185397.jpeg","date_captured":""},{"id":45,"width":203,"height":50,"file_name":"1724218185477.jpeg","license":0,"flickr_url":"C:\\Users\\nikhi\\Pictures\\irctc-captcha\\data\\1724218185477.jpeg","coco_url":"C:\\Users\\nikhi\\Pictures\\irctc-captcha\\data\\1724218185477.jpeg","date_captured":""},{"id":46,"width":203,"height":50,"file_name":"1724218185553.jpeg","license":0,"flickr_url":"C:\\Users\\nikhi\\Pictures\\irctc-captcha\\data\\1724218185553.jpeg","coco_url":"C:\\Users\\nikhi\\Pictures\\irctc-captcha\\data\\1724218185553.jpeg","date_captured":""},{"id":47,"width":203,"height":50,"file_name":"1724218185625.jpeg","license":0,"flickr_url":"C:\\Users\\nikhi\\Pictures\\irctc-captcha\\data\\1724218185625.jpeg","coco_url":"C:\\Users\\nikhi\\Pictures\\irctc-captcha\\data\\1724218185625.jpeg","date_captured":""},{"id":48,"width":203,"height":50,"file_name":"1724218185708.jpeg","license":0,"flickr_url":"C:\\Users\\nikhi\\Pictures\\irctc-captcha\\data\\1724218185708.jpeg","coco_url":"C:\\Users\\nikhi\\Pictures\\irctc-captcha\\data\\1724218185708.jpeg","date_captured":""},{"id":49,"width":203,"height":50,"file_name":"1724218185979.jpeg","license":0,"flickr_url":"C:\\Users\\nikhi\\Pictures\\irctc-captcha\\data\\1724218185979.jpeg","coco_url":"C:\\Users\\nikhi\\Pictures\\irctc-captcha\\data\\1724218185979.jpeg","date_captured":""},{"id":50,"width":203,"height":50,"file_name":"1724218186104.jpeg","license":0,"flickr_url":"C:\\Users\\nikhi\\Pictures\\irctc-captcha\\data\\1724218186104.jpeg","coco_url":"C:\\Users\\nikhi\\Pictures\\irctc-captcha\\data\\1724218186104.jpeg","date_captured":""},{"id":51,"width":203,"height":50,"file_name":"1724218186179.jpeg","license":0,"flickr_url":"C:\\Users\\nikhi\\Pictures\\irctc-captcha\\data\\1724218186179.jpeg","coco_url":"C:\\Users\\nikhi\\Pictures\\irctc-captcha\\data\\1724218186179.jpeg","date_captured":""},{"id":52,"width":203,"height":50,"file_name":"1724218186255.jpeg","license":0,"flickr_url":"C:\\Users\\nikhi\\Pictures\\irctc-captcha\\data\\1724218186255.jpeg","coco_url":"C:\\Users\\nikhi\\Pictures\\irctc-captcha\\data\\1724218186255.jpeg","date_captured":""},{"id":53,"width":203,"height":50,"file_name":"1724218186861.jpeg","license":0,"flickr_url":"C:\\Users\\nikhi\\Pictures\\irctc-captcha\\data\\1724218186861.jpeg","coco_url":"C:\\Users\\nikhi\\Pictures\\irctc-captcha\\data\\1724218186861.jpeg","date_captured":""},{"id":54,"width":203,"height":50,"file_name":"1724218186997.jpeg","license":0,"flickr_url":"C:\\Users\\nikhi\\Pictures\\irctc-captcha\\data\\1724218186997.jpeg","coco_url":"C:\\Users\\nikhi\\Pictures\\irctc-captcha\\data\\1724218186997.jpeg","date_captured":""},{"id":55,"width":203,"height":50,"file_name":"1724218187201.jpeg","license":0,"flickr_url":"C:\\Users\\nikhi\\Pictures\\irctc-captcha\\data\\1724218187201.jpeg","coco_url":"C:\\Users\\nikhi\\Pictures\\irctc-captcha\\data\\1724218187201.jpeg","date_captured":""},{"id":56,"width":203,"height":50,"file_name":"1724218187434.jpeg","license":0,"flickr_url":"C:\\Users\\nikhi\\Pictures\\irctc-captcha\\data\\1724218187434.jpeg","coco_url":"C:\\Users\\nikhi\\Pictures\\irctc-captcha\\data\\1724218187434.jpeg","date_captured":""},{"id":57,"width":203,"height":50,"file_name":"1724218187685.jpeg","license":0,"flickr_url":"C:\\Users\\nikhi\\Pictures\\irctc-captcha\\data\\1724218187685.jpeg","coco_url":"C:\\Users\\nikhi\\Pictures\\irctc-captcha\\data\\1724218187685.jpeg","date_captured":""},{"id":58,"width":203,"height":50,"file_name":"1724218187958.jpeg","license":0,"flickr_url":"C:\\Users\\nikhi\\Pictures\\irctc-captcha\\data\\1724218187958.jpeg","coco_url":"C:\\Users\\nikhi\\Pictures\\irctc-captcha\\data\\1724218187958.jpeg","date_captured":""},{"id":59,"width":203,"height":50,"file_name":"1724218188027.jpeg","license":0,"flickr_url":"C:\\Users\\nikhi\\Pictures\\irctc-captcha\\data\\1724218188027.jpeg","coco_url":"C:\\Users\\nikhi\\Pictures\\irctc-captcha\\data\\1724218188027.jpeg","date_captured":""},{"id":60,"width":203,"height":50,"file_name":"1724218188163.jpeg","license":0,"flickr_url":"C:\\Users\\nikhi\\Pictures\\irctc-captcha\\data\\1724218188163.jpeg","coco_url":"C:\\Users\\nikhi\\Pictures\\irctc-captcha\\data\\1724218188163.jpeg","date_captured":""},{"id":61,"width":203,"height":50,"file_name":"1724218188482.jpeg","license":0,"flickr_url":"C:\\Users\\nikhi\\Pictures\\irctc-captcha\\data\\1724218188482.jpeg","coco_url":"C:\\Users\\nikhi\\Pictures\\irctc-captcha\\data\\1724218188482.jpeg","date_captured":""},{"id":62,"width":203,"height":50,"file_name":"1724218188543.jpeg","license":0,"flickr_url":"C:\\Users\\nikhi\\Pictures\\irctc-captcha\\data\\1724218188543.jpeg","coco_url":"C:\\Users\\nikhi\\Pictures\\irctc-captcha\\data\\1724218188543.jpeg","date_captured":""},{"id":63,"width":203,"height":50,"file_name":"1724218188607.jpeg","license":0,"flickr_url":"C:\\Users\\nikhi\\Pictures\\irctc-captcha\\data\\1724218188607.jpeg","coco_url":"C:\\Users\\nikhi\\Pictures\\irctc-captcha\\data\\1724218188607.jpeg","date_captured":""},{"id":64,"width":203,"height":50,"file_name":"1724218188673.jpeg","license":0,"flickr_url":"C:\\Users\\nikhi\\Pictures\\irctc-captcha\\data\\1724218188673.jpeg","coco_url":"C:\\Users\\nikhi\\Pictures\\irctc-captcha\\data\\1724218188673.jpeg","date_captured":""},{"id":65,"width":203,"height":50,"file_name":"1724218188744.jpeg","license":0,"flickr_url":"C:\\Users\\nikhi\\Pictures\\irctc-captcha\\data\\1724218188744.jpeg","coco_url":"C:\\Users\\nikhi\\Pictures\\irctc-captcha\\data\\1724218188744.jpeg","date_captured":""},{"id":66,"width":203,"height":50,"file_name":"1724218188843.jpeg","license":0,"flickr_url":"C:\\Users\\nikhi\\Pictures\\irctc-captcha\\data\\1724218188843.jpeg","coco_url":"C:\\Users\\nikhi\\Pictures\\irctc-captcha\\data\\1724218188843.jpeg","date_captured":""},{"id":67,"width":203,"height":50,"file_name":"1724218188915.jpeg","license":0,"flickr_url":"C:\\Users\\nikhi\\Pictures\\irctc-captcha\\data\\1724218188915.jpeg","coco_url":"C:\\Users\\nikhi\\Pictures\\irctc-captcha\\data\\1724218188915.jpeg","date_captured":""},{"id":68,"width":203,"height":50,"file_name":"1724218189019.jpeg","license":0,"flickr_url":"C:\\Users\\nikhi\\Pictures\\irctc-captcha\\data\\1724218189019.jpeg","coco_url":"C:\\Users\\nikhi\\Pictures\\irctc-captcha\\data\\1724218189019.jpeg","date_captured":""},{"id":69,"width":203,"height":50,"file_name":"1724218189092.jpeg","license":0,"flickr_url":"C:\\Users\\nikhi\\Pictures\\irctc-captcha\\data\\1724218189092.jpeg","coco_url":"C:\\Users\\nikhi\\Pictures\\irctc-captcha\\data\\1724218189092.jpeg","date_captured":""},{"id":70,"width":203,"height":50,"file_name":"1724218189206.jpeg","license":0,"flickr_url":"C:\\Users\\nikhi\\Pictures\\irctc-captcha\\data\\1724218189206.jpeg","coco_url":"C:\\Users\\nikhi\\Pictures\\irctc-captcha\\data\\1724218189206.jpeg","date_captured":""},{"id":71,"width":203,"height":50,"file_name":"1724218189529.jpeg","license":0,"flickr_url":"C:\\Users\\nikhi\\Pictures\\irctc-captcha\\data\\1724218189529.jpeg","coco_url":"C:\\Users\\nikhi\\Pictures\\irctc-captcha\\data\\1724218189529.jpeg","date_captured":""},{"id":72,"width":203,"height":50,"file_name":"1724218189636.jpeg","license":0,"flickr_url":"C:\\Users\\nikhi\\Pictures\\irctc-captcha\\data\\1724218189636.jpeg","coco_url":"C:\\Users\\nikhi\\Pictures\\irctc-captcha\\data\\1724218189636.jpeg","date_captured":""},{"id":73,"width":203,"height":50,"file_name":"1724218189695.jpeg","license":0,"flickr_url":"C:\\Users\\nikhi\\Pictures\\irctc-captcha\\data\\1724218189695.jpeg","coco_url":"C:\\Users\\nikhi\\Pictures\\irctc-captcha\\data\\1724218189695.jpeg","date_captured":""},{"id":74,"width":203,"height":50,"file_name":"1724218189809.jpeg","license":0,"flickr_url":"C:\\Users\\nikhi\\Pictures\\irctc-captcha\\data\\1724218189809.jpeg","coco_url":"C:\\Users\\nikhi\\Pictures\\irctc-captcha\\data\\1724218189809.jpeg","date_captured":""},{"id":75,"width":203,"height":50,"file_name":"1724218189894.jpeg","license":0,"flickr_url":"C:\\Users\\nikhi\\Pictures\\irctc-captcha\\data\\1724218189894.jpeg","coco_url":"C:\\Users\\nikhi\\Pictures\\irctc-captcha\\data\\1724218189894.jpeg","date_captured":""},{"id":76,"width":203,"height":50,"file_name":"1724218189986.jpeg","license":0,"flickr_url":"C:\\Users\\nikhi\\Pictures\\irctc-captcha\\data\\1724218189986.jpeg","coco_url":"C:\\Users\\nikhi\\Pictures\\irctc-captcha\\data\\1724218189986.jpeg","date_captured":""},{"id":77,"width":203,"height":50,"file_name":"1724218190057.jpeg","license":0,"flickr_url":"C:\\Users\\nikhi\\Pictures\\irctc-captcha\\data\\1724218190057.jpeg","coco_url":"C:\\Users\\nikhi\\Pictures\\irctc-captcha\\data\\1724218190057.jpeg","date_captured":""},{"id":78,"width":203,"height":50,"file_name":"1724218190131.jpeg","license":0,"flickr_url":"C:\\Users\\nikhi\\Pictures\\irctc-captcha\\data\\1724218190131.jpeg","coco_url":"C:\\Users\\nikhi\\Pictures\\irctc-captcha\\data\\1724218190131.jpeg","date_captured":""},{"id":79,"width":203,"height":50,"file_name":"1724218190434.jpeg","license":0,"flickr_url":"C:\\Users\\nikhi\\Pictures\\irctc-captcha\\data\\1724218190434.jpeg","coco_url":"C:\\Users\\nikhi\\Pictures\\irctc-captcha\\data\\1724218190434.jpeg","date_captured":""},{"id":80,"width":203,"height":50,"file_name":"1724218190509.jpeg","license":0,"flickr_url":"C:\\Users\\nikhi\\Pictures\\irctc-captcha\\data\\1724218190509.jpeg","coco_url":"C:\\Users\\nikhi\\Pictures\\irctc-captcha\\data\\1724218190509.jpeg","date_captured":""},{"id":81,"width":203,"height":50,"file_name":"1724218190579.jpeg","license":0,"flickr_url":"C:\\Users\\nikhi\\Pictures\\irctc-captcha\\data\\1724218190579.jpeg","coco_url":"C:\\Users\\nikhi\\Pictures\\irctc-captcha\\data\\1724218190579.jpeg","date_captured":""},{"id":82,"width":203,"height":50,"file_name":"1724218190718.jpeg","license":0,"flickr_url":"C:\\Users\\nikhi\\Pictures\\irctc-captcha\\data\\1724218190718.jpeg","coco_url":"C:\\Users\\nikhi\\Pictures\\irctc-captcha\\data\\1724218190718.jpeg","date_captured":""},{"id":83,"width":203,"height":50,"file_name":"1724218190836.jpeg","license":0,"flickr_url":"C:\\Users\\nikhi\\Pictures\\irctc-captcha\\data\\1724218190836.jpeg","coco_url":"C:\\Users\\nikhi\\Pictures\\irctc-captcha\\data\\1724218190836.jpeg","date_captured":""},{"id":84,"width":203,"height":50,"file_name":"1724218190930.jpeg","license":0,"flickr_url":"C:\\Users\\nikhi\\Pictures\\irctc-captcha\\data\\1724218190930.jpeg","coco_url":"C:\\Users\\nikhi\\Pictures\\irctc-captcha\\data\\1724218190930.jpeg","date_captured":""},{"id":85,"width":203,"height":50,"file_name":"1724218191023.jpeg","license":0,"flickr_url":"C:\\Users\\nikhi\\Pictures\\irctc-captcha\\data\\1724218191023.jpeg","coco_url":"C:\\Users\\nikhi\\Pictures\\irctc-captcha\\data\\1724218191023.jpeg","date_captured":""},{"id":86,"width":203,"height":50,"file_name":"1724218191093.jpeg","license":0,"flickr_url":"C:\\Users\\nikhi\\Pictures\\irctc-captcha\\data\\1724218191093.jpeg","coco_url":"C:\\Users\\nikhi\\Pictures\\irctc-captcha\\data\\1724218191093.jpeg","date_captured":""},{"id":87,"width":203,"height":50,"file_name":"1724218191170.jpeg","license":0,"flickr_url":"C:\\Users\\nikhi\\Pictures\\irctc-captcha\\data\\1724218191170.jpeg","coco_url":"C:\\Users\\nikhi\\Pictures\\irctc-captcha\\data\\1724218191170.jpeg","date_captured":""},{"id":88,"width":203,"height":50,"file_name":"1724218191327.jpeg","license":0,"flickr_url":"C:\\Users\\nikhi\\Pictures\\irctc-captcha\\data\\1724218191327.jpeg","coco_url":"C:\\Users\\nikhi\\Pictures\\irctc-captcha\\data\\1724218191327.jpeg","date_captured":""},{"id":89,"width":203,"height":50,"file_name":"1724218191416.jpeg","license":0,"flickr_url":"C:\\Users\\nikhi\\Pictures\\irctc-captcha\\data\\1724218191416.jpeg","coco_url":"C:\\Users\\nikhi\\Pictures\\irctc-captcha\\data\\1724218191416.jpeg","date_captured":""},{"id":90,"width":203,"height":50,"file_name":"1724218191493.jpeg","license":0,"flickr_url":"C:\\Users\\nikhi\\Pictures\\irctc-captcha\\data\\1724218191493.jpeg","coco_url":"C:\\Users\\nikhi\\Pictures\\irctc-captcha\\data\\1724218191493.jpeg","date_captured":""},{"id":91,"width":203,"height":50,"file_name":"1724218191648.jpeg","license":0,"flickr_url":"C:\\Users\\nikhi\\Pictures\\irctc-captcha\\data\\1724218191648.jpeg","coco_url":"C:\\Users\\nikhi\\Pictures\\irctc-captcha\\data\\1724218191648.jpeg","date_captured":""},{"id":92,"width":203,"height":50,"file_name":"1724218191732.jpeg","license":0,"flickr_url":"C:\\Users\\nikhi\\Pictures\\irctc-captcha\\data\\1724218191732.jpeg","coco_url":"C:\\Users\\nikhi\\Pictures\\irctc-captcha\\data\\1724218191732.jpeg","date_captured":""},{"id":93,"width":203,"height":50,"file_name":"1724218192024.jpeg","license":0,"flickr_url":"C:\\Users\\nikhi\\Pictures\\irctc-captcha\\data\\1724218192024.jpeg","coco_url":"C:\\Users\\nikhi\\Pictures\\irctc-captcha\\data\\1724218192024.jpeg","date_captured":""},{"id":94,"width":203,"height":50,"file_name":"1724218192490.jpeg","license":0,"flickr_url":"C:\\Users\\nikhi\\Pictures\\irctc-captcha\\data\\1724218192490.jpeg","coco_url":"C:\\Users\\nikhi\\Pictures\\irctc-captcha\\data\\1724218192490.jpeg","date_captured":""},{"id":95,"width":203,"height":50,"file_name":"1724218192778.jpeg","license":0,"flickr_url":"C:\\Users\\nikhi\\Pictures\\irctc-captcha\\data\\1724218192778.jpeg","coco_url":"C:\\Users\\nikhi\\Pictures\\irctc-captcha\\data\\1724218192778.jpeg","date_captured":""},{"id":96,"width":203,"height":50,"file_name":"1724218193155.jpeg","license":0,"flickr_url":"C:\\Users\\nikhi\\Pictures\\irctc-captcha\\data\\1724218193155.jpeg","coco_url":"C:\\Users\\nikhi\\Pictures\\irctc-captcha\\data\\1724218193155.jpeg","date_captured":""},{"id":97,"width":203,"height":50,"file_name":"1724218194672.jpeg","license":0,"flickr_url":"C:\\Users\\nikhi\\Pictures\\irctc-captcha\\data\\1724218194672.jpeg","coco_url":"C:\\Users\\nikhi\\Pictures\\irctc-captcha\\data\\1724218194672.jpeg","date_captured":""},{"id":98,"width":203,"height":50,"file_name":"1724218197539.jpeg","license":0,"flickr_url":"C:\\Users\\nikhi\\Pictures\\irctc-captcha\\data\\1724218197539.jpeg","coco_url":"C:\\Users\\nikhi\\Pictures\\irctc-captcha\\data\\1724218197539.jpeg","date_captured":""},{"id":99,"width":203,"height":50,"file_name":"1724218202303.jpeg","license":0,"flickr_url":"C:\\Users\\nikhi\\Pictures\\irctc-captcha\\data\\1724218202303.jpeg","coco_url":"C:\\Users\\nikhi\\Pictures\\irctc-captcha\\data\\1724218202303.jpeg","date_captured":""},{"id":100,"width":203,"height":50,"file_name":"1724218349920.jpeg","license":0,"flickr_url":"C:\\Users\\nikhi\\Pictures\\irctc-captcha\\data\\1724218349920.jpeg","coco_url":"C:\\Users\\nikhi\\Pictures\\irctc-captcha\\data\\1724218349920.jpeg","date_captured":""}],"annotations":[{"segmentation":[[14,10,27,10,27,36,14,36]],"area":338,"bbox":[14,10,13,26],"iscrowd":0,"id":1,"image_id":1,"category_id":6},{"segmentation":[[27,8,43,8,43,40,27,40]],"area":512,"bbox":[27,8,16,32],"iscrowd":0,"id":2,"image_id":1,"category_id":7},{"segmentation":[[44,1,71,1,71,32,44,32]],"area":837,"bbox":[44,1,27,31],"iscrowd":0,"id":3,"image_id":1,"category_id":8},{"segmentation":[[73,12,102,12,102,44,73,44]],"area":928,"bbox":[73,12,29,32],"iscrowd":0,"id":4,"image_id":1,"category_id":9},{"segmentation":[[107,6,129,6,129,39,107,39]],"area":726,"bbox":[107,6,22,33],"iscrowd":0,"id":5,"image_id":1,"category_id":10},{"segmentation":[[13,17,33,17,33,43,13,43]],"area":520,"bbox":[13,17,20,26],"iscrowd":0,"id":6,"image_id":2,"category_id":11},{"segmentation":[[36,17,56,17,56,42,36,42]],"area":500,"bbox":[36,17,20,25],"iscrowd":0,"id":7,"image_id":2,"category_id":11},{"segmentation":[[58,7,77,7,77,33,58,33]],"area":494,"bbox":[58,7,19,26],"iscrowd":0,"id":8,"image_id":2,"category_id":12},{"segmentation":[[80,10,102,10,102,43,80,43]],"area":726,"bbox":[80,10,22,33],"iscrowd":0,"id":9,"image_id":2,"category_id":10},{"segmentation":[[105,0,131,0,131,32,105,32]],"area":832,"bbox":[105,0,26,32],"iscrowd":0,"id":10,"image_id":2,"category_id":13},{"segmentation":[[136,6,163,6,163,38,136,38]],"area":864,"bbox":[136,6,27,32],"iscrowd":0,"id":11,"image_id":2,"category_id":14},{"segmentation":[[9,2,49,2,49,34,9,34]],"area":1280,"bbox":[9,2,40,32],"iscrowd":0,"id":12,"image_id":3,"category_id":15},{"segmentation":[[52,17,73,17,73,43,52,43]],"area":546,"bbox":[52,17,21,26],"iscrowd":0,"id":13,"image_id":3,"category_id":12},{"segmentation":[[75,8,101,8,101,41,75,41]],"area":858,"bbox":[75,8,26,33],"iscrowd":0,"id":14,"image_id":3,"category_id":16},{"segmentation":[[106,6,130,6,130,39,106,39]],"area":792,"bbox":[106,6,24,33],"iscrowd":0,"id":15,"image_id":3,"category_id":17},{"segmentation":[[132,7,157,7,157,39,132,39]],"area":800,"bbox":[132,7,25,32],"iscrowd":0,"id":16,"image_id":3,"category_id":18},{"segmentation":[[158,18,180,18,180,44,158,44]],"area":572,"bbox":[158,18,22,26],"iscrowd":0,"id":17,"image_id":3,"category_id":19},{"segmentation":[[11,9,34,9,34,40,11,40]],"area":713,"bbox":[11,9,23,31],"iscrowd":0,"id":18,"image_id":4,"category_id":2},{"segmentation":[[39,10,64,10,64,42,39,42]],"area":800,"bbox":[39,10,25,32],"iscrowd":0,"id":19,"image_id":4,"category_id":20},{"segmentation":[[66,11,86,11,86,43,66,43]],"area":640,"bbox":[66,11,20,32],"iscrowd":0,"id":20,"image_id":4,"category_id":21},{"segmentation":[[86,4,112,4,112,36,86,36]],"area":832,"bbox":[86,4,26,32],"iscrowd":0,"id":21,"image_id":4,"category_id":16},{"segmentation":[[12,19,32,19,32,44,12,44]],"area":500,"bbox":[12,19,20,25],"iscrowd":0,"id":22,"image_id":5,"category_id":12},{"segmentation":[[36,9,55,9,55,41,36,41]],"area":608,"bbox":[36,9,19,32],"iscrowd":0,"id":23,"image_id":5,"category_id":22},{"segmentation":[[56,12,77,12,77,44,56,44]],"area":672,"bbox":[56,12,21,32],"iscrowd":0,"id":24,"image_id":5,"category_id":10},{"segmentation":[[79,10,105,10,105,42,79,42]],"area":832,"bbox":[79,10,26,32],"iscrowd":0,"id":25,"image_id":5,"category_id":16},{"segmentation":[[109,5,131,5,131,37,109,37]],"area":704,"bbox":[109,5,22,32],"iscrowd":0,"id":26,"image_id":5,"category_id":3},{"segmentation":[[134,12,171,12,171,49,134,49]],"area":1369,"bbox":[134,12,37,37],"iscrowd":0,"id":27,"image_id":5,"category_id":23},{"segmentation":[[11,19,33,19,33,50,11,50]],"area":682,"bbox":[11,19,22,31],"iscrowd":0,"id":28,"image_id":6,"category_id":24},{"segmentation":[[36,4,72,4,72,41,36,41]],"area":1332,"bbox":[36,4,36,37],"iscrowd":0,"id":29,"image_id":6,"category_id":23},{"segmentation":[[74,11,97,11,97,43,74,43]],"area":736,"bbox":[74,11,23,32],"iscrowd":0,"id":30,"image_id":6,"category_id":2},{"segmentation":[[98,13,124,13,124,44,98,44]],"area":806,"bbox":[98,13,26,31],"iscrowd":0,"id":31,"image_id":6,"category_id":25},{"segmentation":[[129,15,151,15,151,48,129,48]],"area":726,"bbox":[129,15,22,33],"iscrowd":0,"id":32,"image_id":6,"category_id":26},{"segmentation":[[155,8,179,8,179,40,155,40]],"area":768,"bbox":[155,8,24,32],"iscrowd":0,"id":33,"image_id":6,"category_id":18},{"segmentation":[[12,10,49,10,49,47,12,47]],"area":1369,"bbox":[12,10,37,37],"iscrowd":0,"id":34,"image_id":7,"category_id":23},{"segmentation":[[52,2,77,2,77,34,52,34]],"area":800,"bbox":[52,2,25,32],"iscrowd":0,"id":35,"image_id":7,"category_id":27},{"segmentation":[[80,15,113,15,113,42,80,42]],"area":891,"bbox":[80,15,33,27],"iscrowd":0,"id":36,"image_id":7,"category_id":29},{"segmentation":[[113,12,129,12,129,44,113,44]],"area":512,"bbox":[113,12,16,32],"iscrowd":0,"id":37,"image_id":7,"category_id":28},{"segmentation":[[134,13,165,13,165,46,134,46]],"area":1023,"bbox":[134,13,31,33],"iscrowd":0,"id":38,"image_id":7,"category_id":30},{"segmentation":[[11,13,34,13,34,46,11,46]],"area":759,"bbox":[11,13,23,33],"iscrowd":0,"id":39,"image_id":8,"category_id":24},{"segmentation":[[37,13,62,13,62,45,37,45]],"area":800,"bbox":[37,13,25,32],"iscrowd":0,"id":40,"image_id":8,"category_id":31},{"segmentation":[[63,7,84,7,84,38,63,38]],"area":651,"bbox":[63,7,21,31],"iscrowd":0,"id":41,"image_id":8,"category_id":32},{"segmentation":[[87,10,114,10,114,42,87,42]],"area":864,"bbox":[87,10,27,32],"iscrowd":0,"id":42,"image_id":8,"category_id":14},{"segmentation":[[11,13,33,13,33,47,11,47]],"area":748,"bbox":[11,13,22,34],"iscrowd":0,"id":43,"image_id":9,"category_id":24},{"segmentation":[[34,13,59,13,59,44,34,44]],"area":775,"bbox":[34,13,25,31],"iscrowd":0,"id":44,"image_id":9,"category_id":8},{"segmentation":[[66,9,86,9,86,41,66,41]],"area":640,"bbox":[66,9,20,32],"iscrowd":0,"id":45,"image_id":9,"category_id":32},{"segmentation":[[88,12,115,12,115,49,88,49]],"area":999,"bbox":[88,12,27,37],"iscrowd":0,"id":46,"image_id":9,"category_id":33},{"segmentation":[[120,10,140,10,140,43,120,43]],"area":660,"bbox":[120,10,20,33],"iscrowd":0,"id":47,"image_id":9,"category_id":34},{"segmentation":[[143,21,171,21,171,35,143,35]],"area":392,"bbox":[143,21,28,14],"iscrowd":0,"id":48,"image_id":9,"category_id":35},{"segmentation":[[9,1,49,1,49,32,9,32]],"area":1240,"bbox":[9,1,40,31],"iscrowd":0,"id":49,"image_id":10,"category_id":15},{"segmentation":[[53,5,75,5,75,38,53,38]],"area":726,"bbox":[53,5,22,33],"iscrowd":0,"id":50,"image_id":10,"category_id":3},{"segmentation":[[75,8,101,8,101,40,75,40]],"area":832,"bbox":[75,8,26,32],"iscrowd":0,"id":51,"image_id":10,"category_id":25},{"segmentation":[[106,18,128,18,128,50,106,50]],"area":704,"bbox":[106,18,22,32],"iscrowd":0,"id":52,"image_id":10,"category_id":26},{"segmentation":[[13,10,33,10,33,42,13,42]],"area":640,"bbox":[13,10,20,32],"iscrowd":0,"id":53,"image_id":11,"category_id":1},{"segmentation":[[35,9,57,9,57,40,35,40]],"area":682,"bbox":[35,9,22,31],"iscrowd":0,"id":54,"image_id":11,"category_id":2},{"segmentation":[[62,11,83,11,83,44,62,44]],"area":693,"bbox":[62,11,21,33],"iscrowd":0,"id":55,"image_id":11,"category_id":36},{"segmentation":[[86,9,105,9,105,41,86,41]],"area":608,"bbox":[86,9,19,32],"iscrowd":0,"id":56,"image_id":11,"category_id":22},{"segmentation":[[108,2,132,2,132,34,108,34]],"area":768,"bbox":[108,2,24,32],"iscrowd":0,"id":57,"image_id":11,"category_id":31},{"segmentation":[[12,24,40,24,40,38,12,38]],"area":392,"bbox":[12,24,28,14],"iscrowd":0,"id":58,"image_id":12,"category_id":35},{"segmentation":[[39,10,68,10,68,42,39,42]],"area":928,"bbox":[39,10,29,32],"iscrowd":0,"id":59,"image_id":12,"category_id":9},{"segmentation":[[70,7,99,7,99,38,70,38]],"area":899,"bbox":[70,7,29,31],"iscrowd":0,"id":60,"image_id":12,"category_id":9},{"segmentation":[[103,7,123,7,123,33,103,33]],"area":520,"bbox":[103,7,20,26],"iscrowd":0,"id":61,"image_id":12,"category_id":12},{"segmentation":[[126,19,146,19,146,45,126,45]],"area":520,"bbox":[126,19,20,26],"iscrowd":0,"id":62,"image_id":12,"category_id":12},{"segmentation":[[152,6,171,6,171,39,152,39]],"area":627,"bbox":[152,6,19,33],"iscrowd":0,"id":63,"image_id":12,"category_id":36},{"segmentation":[[11,19,34,19,34,50,11,50]],"area":713,"bbox":[11,19,23,31],"iscrowd":0,"id":64,"image_id":13,"category_id":26},{"segmentation":[[35,6,57,6,57,38,35,38]],"area":704,"bbox":[35,6,22,32],"iscrowd":0,"id":65,"image_id":13,"category_id":10},{"segmentation":[[58,10,74,10,74,40,58,40]],"area":480,"bbox":[58,10,16,30],"iscrowd":0,"id":66,"image_id":13,"category_id":7},{"segmentation":[[79,12,100,12,100,43,79,43]],"area":651,"bbox":[79,12,21,31],"iscrowd":0,"id":67,"image_id":13,"category_id":37},{"segmentation":[[12,1,34,1,34,32,12,32]],"area":682,"bbox":[12,1,22,31],"iscrowd":0,"id":68,"image_id":14,"category_id":5},{"segmentation":[[37,13,58,13,58,46,37,46]],"area":693,"bbox":[37,13,21,33],"iscrowd":0,"id":69,"image_id":14,"category_id":24},{"segmentation":[[61,19,96,19,96,44,61,44]],"area":875,"bbox":[61,19,35,25],"iscrowd":0,"id":70,"image_id":14,"category_id":29},{"segmentation":[[97,10,134,10,134,47,97,47]],"area":1369,"bbox":[97,10,37,37],"iscrowd":0,"id":71,"image_id":14,"category_id":23},{"segmentation":[[12,8,49,8,49,45,12,45]],"area":1369,"bbox":[12,8,37,37],"iscrowd":0,"id":72,"image_id":15,"category_id":23},{"segmentation":[[51,12,78,12,78,44,51,44]],"area":864,"bbox":[51,12,27,32],"iscrowd":0,"id":73,"image_id":15,"category_id":13},{"segmentation":[[82,17,110,17,110,32,82,32]],"area":420,"bbox":[82,17,28,15],"iscrowd":0,"id":74,"image_id":15,"category_id":35},{"segmentation":[[112,11,131,11,131,42,112,42]],"area":589,"bbox":[112,11,19,31],"iscrowd":0,"id":75,"image_id":15,"category_id":22},{"segmentation":[[131,8,154,8,154,41,131,41]],"area":759,"bbox":[131,8,23,33],"iscrowd":0,"id":76,"image_id":15,"category_id":10},{"segmentation":[[9,8,35,8,35,39,9,39]],"area":806,"bbox":[9,8,26,31],"iscrowd":0,"id":77,"image_id":16,"category_id":25},{"segmentation":[[41,9,62,9,62,42,41,42]],"area":693,"bbox":[41,9,21,33],"iscrowd":0,"id":78,"image_id":16,"category_id":34},{"segmentation":[[63,13,85,13,85,38,63,38]],"area":550,"bbox":[63,13,22,25],"iscrowd":0,"id":79,"image_id":16,"category_id":19},{"segmentation":[[88,10,110,10,110,42,88,42]],"area":704,"bbox":[88,10,22,32],"iscrowd":0,"id":80,"image_id":16,"category_id":10},{"segmentation":[[13,15,33,15,33,40,13,40]],"area":500,"bbox":[13,15,20,25],"iscrowd":0,"id":81,"image_id":17,"category_id":38},{"segmentation":[[35,13,56,13,56,46,35,46]],"area":693,"bbox":[35,13,21,33],"iscrowd":0,"id":82,"image_id":17,"category_id":26},{"segmentation":[[57,9,73,9,73,42,57,42]],"area":528,"bbox":[57,9,16,33],"iscrowd":0,"id":83,"image_id":17,"category_id":28},{"segmentation":[[78,9,105,9,105,41,78,41]],"area":864,"bbox":[78,9,27,32],"iscrowd":0,"id":84,"image_id":17,"category_id":14},{"segmentation":[[107,20,127,20,127,44,107,44]],"area":480,"bbox":[107,20,20,24],"iscrowd":0,"id":85,"image_id":17,"category_id":11},{"segmentation":[[9,12,35,12,35,43,9,43]],"area":806,"bbox":[9,12,26,31],"iscrowd":0,"id":86,"image_id":18,"category_id":25},{"segmentation":[[41,12,62,12,62,44,41,44]],"area":672,"bbox":[41,12,21,32],"iscrowd":0,"id":87,"image_id":18,"category_id":5},{"segmentation":[[66,1,87,1,87,32,66,32]],"area":651,"bbox":[66,1,21,31],"iscrowd":0,"id":88,"image_id":18,"category_id":4},{"segmentation":[[90,2,115,2,115,35,90,35]],"area":825,"bbox":[90,2,25,33],"iscrowd":0,"id":89,"image_id":18,"category_id":27},{"segmentation":[[11,0,26,0,26,32,11,32]],"area":480,"bbox":[11,0,15,32],"iscrowd":0,"id":90,"image_id":19,"category_id":28},{"segmentation":[[30,13,55,13,55,44,30,44]],"area":775,"bbox":[30,13,25,31],"iscrowd":0,"id":91,"image_id":19,"category_id":27},{"segmentation":[[57,1,86,1,86,38,57,38]],"area":1073,"bbox":[57,1,29,37],"iscrowd":0,"id":92,"image_id":19,"category_id":33},{"segmentation":[[90,7,114,7,114,39,90,39]],"area":768,"bbox":[90,7,24,32],"iscrowd":0,"id":93,"image_id":19,"category_id":20},{"segmentation":[[116,17,135,17,135,42,116,42]],"area":475,"bbox":[116,17,19,25],"iscrowd":0,"id":94,"image_id":19,"category_id":12},{"segmentation":[[139,5,160,5,160,39,139,39]],"area":714,"bbox":[139,5,21,34],"iscrowd":0,"id":95,"image_id":19,"category_id":36},{"segmentation":[[12,8,31,8,31,33,12,33]],"area":475,"bbox":[12,8,19,25],"iscrowd":0,"id":96,"image_id":20,"category_id":12},{"segmentation":[[36,12,60,12,60,44,36,44]],"area":768,"bbox":[36,12,24,32],"iscrowd":0,"id":97,"image_id":20,"category_id":18},{"segmentation":[[62,10,88,10,88,43,62,43]],"area":858,"bbox":[62,10,26,33],"iscrowd":0,"id":98,"image_id":20,"category_id":13},{"segmentation":[[92,6,120,6,120,38,92,38]],"area":896,"bbox":[92,6,28,32],"iscrowd":0,"id":99,"image_id":20,"category_id":13},{"segmentation":[[123,13,147,13,147,44,123,44]],"area":744,"bbox":[123,13,24,31],"iscrowd":0,"id":100,"image_id":20,"category_id":18},{"segmentation":[[13,8,35,8,35,41,13,41]],"area":726,"bbox":[13,8,22,33],"iscrowd":0,"id":101,"image_id":21,"category_id":39},{"segmentation":[[37,12,71,12,71,40,37,40]],"area":952,"bbox":[37,12,34,28],"iscrowd":0,"id":102,"image_id":21,"category_id":29},{"segmentation":[[72,15,93,15,93,41,72,41]],"area":546,"bbox":[72,15,21,26],"iscrowd":0,"id":103,"image_id":21,"category_id":38},{"segmentation":[[96,11,111,11,111,36,96,36]],"area":375,"bbox":[96,11,15,25],"iscrowd":0,"id":104,"image_id":21,"category_id":6},{"segmentation":[[112,7,133,7,133,38,112,38]],"area":651,"bbox":[112,7,21,31],"iscrowd":0,"id":105,"image_id":21,"category_id":4},{"segmentation":[[10,8,26,8,26,40,10,40]],"area":512,"bbox":[10,8,16,32],"iscrowd":0,"id":106,"image_id":22,"category_id":28},{"segmentation":[[29,10,56,10,56,43,29,43]],"area":891,"bbox":[29,10,27,33],"iscrowd":0,"id":107,"image_id":22,"category_id":13},{"segmentation":[[61,14,97,14,97,50,61,50]],"area":1296,"bbox":[61,14,36,36],"iscrowd":0,"id":108,"image_id":22,"category_id":23},{"segmentation":[[100,19,121,19,121,44,100,44]],"area":525,"bbox":[100,19,21,25],"iscrowd":0,"id":109,"image_id":22,"category_id":38},{"segmentation":[[11,7,34,7,34,38,11,38]],"area":713,"bbox":[11,7,23,31],"iscrowd":0,"id":110,"image_id":23,"category_id":2},{"segmentation":[[37,9,60,9,60,41,37,41]],"area":736,"bbox":[37,9,23,32],"iscrowd":0,"id":111,"image_id":23,"category_id":2},{"segmentation":[[63,12,86,12,86,44,63,44]],"area":736,"bbox":[63,12,23,32],"iscrowd":0,"id":112,"image_id":23,"category_id":37},{"segmentation":[[87,17,108,17,108,42,87,42]],"area":525,"bbox":[87,17,21,25],"iscrowd":0,"id":113,"image_id":23,"category_id":38},{"segmentation":[[111,9,136,9,136,41,111,41]],"area":800,"bbox":[111,9,25,32],"iscrowd":0,"id":114,"image_id":23,"category_id":17},{"segmentation":[[11,13,40,13,40,49,11,49]],"area":1044,"bbox":[11,13,29,36],"iscrowd":0,"id":115,"image_id":24,"category_id":33},{"segmentation":[[43,11,66,11,66,45,43,45]],"area":782,"bbox":[43,11,23,34],"iscrowd":0,"id":116,"image_id":24,"category_id":39},{"segmentation":[[66,9,93,9,93,42,66,42]],"area":891,"bbox":[66,9,27,33],"iscrowd":0,"id":117,"image_id":24,"category_id":13},{"segmentation":[[97,9,118,9,118,34,97,34]],"area":525,"bbox":[97,9,21,25],"iscrowd":0,"id":118,"image_id":24,"category_id":11},{"segmentation":[[119,10,146,10,146,42,119,42]],"area":864,"bbox":[119,10,27,32],"iscrowd":0,"id":119,"image_id":24,"category_id":13},{"segmentation":[[12,6,33,6,33,39,12,39]],"area":693,"bbox":[12,6,21,33],"iscrowd":0,"id":120,"image_id":25,"category_id":4},{"segmentation":[[36,8,56,8,56,41,36,41]],"area":660,"bbox":[36,8,20,33],"iscrowd":0,"id":121,"image_id":25,"category_id":32},{"segmentation":[[59,9,83,9,83,39,59,39]],"area":720,"bbox":[59,9,24,30],"iscrowd":0,"id":122,"image_id":25,"category_id":18},{"segmentation":[[83,7,93,7,93,47,83,47]],"area":400,"bbox":[83,7,10,40],"iscrowd":0,"id":123,"image_id":25,"category_id":40},{"segmentation":[[100,1,121,1,121,33,100,33]],"area":672,"bbox":[100,1,21,32],"iscrowd":0,"id":124,"image_id":25,"category_id":39},{"segmentation":[[123,12,148,12,148,44,123,44]],"area":800,"bbox":[123,12,25,32],"iscrowd":0,"id":125,"image_id":25,"category_id":18},{"segmentation":[[9,10,34,10,34,41,9,41]],"area":775,"bbox":[9,10,25,31],"iscrowd":0,"id":126,"image_id":26,"category_id":8},{"segmentation":[[37,9,66,9,66,42,37,42]],"area":957,"bbox":[37,9,29,33],"iscrowd":0,"id":127,"image_id":26,"category_id":9},{"segmentation":[[71,8,93,8,93,43,71,43]],"area":770,"bbox":[71,8,22,35],"iscrowd":0,"id":128,"image_id":26,"category_id":24},{"segmentation":[[96,8,118,8,118,41,96,41]],"area":726,"bbox":[96,8,22,33],"iscrowd":0,"id":129,"image_id":26,"category_id":5},{"segmentation":[[122,8,142,8,142,41,122,41]],"area":660,"bbox":[122,8,20,33],"iscrowd":0,"id":130,"image_id":26,"category_id":21},{"segmentation":[[13,9,35,9,35,42,13,42]],"area":726,"bbox":[13,9,22,33],"iscrowd":0,"id":131,"image_id":27,"category_id":39},{"segmentation":[[37,11,62,11,62,42,37,42]],"area":775,"bbox":[37,11,25,31],"iscrowd":0,"id":132,"image_id":27,"category_id":17},{"segmentation":[[63,1,85,1,85,32,63,32]],"area":682,"bbox":[63,1,22,31],"iscrowd":0,"id":133,"image_id":27,"category_id":3},{"segmentation":[[86,5,95,5,95,45,86,45]],"area":360,"bbox":[86,5,9,40],"iscrowd":0,"id":134,"image_id":27,"category_id":40},{"segmentation":[[11,9,32,9,32,35,11,35]],"area":546,"bbox":[11,9,21,26],"iscrowd":0,"id":135,"image_id":28,"category_id":12},{"segmentation":[[35,7,56,7,56,39,35,39]],"area":672,"bbox":[35,7,21,32],"iscrowd":0,"id":136,"image_id":28,"category_id":32},{"segmentation":[[57,13,80,13,80,45,57,45]],"area":736,"bbox":[57,13,23,32],"iscrowd":0,"id":137,"image_id":28,"category_id":2},{"segmentation":[[84,12,109,12,109,45,84,45]],"area":825,"bbox":[84,12,25,33],"iscrowd":0,"id":138,"image_id":28,"category_id":31},{"segmentation":[[112,21,139,21,139,36,112,36]],"area":405,"bbox":[112,21,27,15],"iscrowd":0,"id":139,"image_id":28,"category_id":35},{"segmentation":[[12,12,47,12,47,37,12,37]],"area":875,"bbox":[12,12,35,25],"iscrowd":0,"id":140,"image_id":29,"category_id":29},{"segmentation":[[48,13,70,13,70,44,48,44]],"area":682,"bbox":[48,13,22,31],"iscrowd":0,"id":141,"image_id":29,"category_id":2},{"segmentation":[[75,10,97,10,97,43,75,43]],"area":726,"bbox":[75,10,22,33],"iscrowd":0,"id":142,"image_id":29,"category_id":39},{"segmentation":[[98,6,119,6,119,39,98,39]],"area":693,"bbox":[98,6,21,33],"iscrowd":0,"id":143,"image_id":29,"category_id":1},{"segmentation":[[123,12,148,12,148,44,123,44]],"area":800,"bbox":[123,12,25,32],"iscrowd":0,"id":144,"image_id":29,"category_id":31},{"segmentation":[[12,6,34,6,34,38,12,38]],"area":704,"bbox":[12,6,22,32],"iscrowd":0,"id":145,"image_id":30,"category_id":21},{"segmentation":[[35,7,57,7,57,41,35,41]],"area":748,"bbox":[35,7,22,34],"iscrowd":0,"id":146,"image_id":30,"category_id":10},{"segmentation":[[60,12,81,12,81,44,60,44]],"area":672,"bbox":[60,12,21,32],"iscrowd":0,"id":147,"image_id":30,"category_id":37},{"segmentation":[[82,12,108,12,108,44,82,44]],"area":832,"bbox":[82,12,26,32],"iscrowd":0,"id":148,"image_id":30,"category_id":13},{"segmentation":[[11,17,31,17,31,42,11,42]],"area":500,"bbox":[11,17,20,25],"iscrowd":0,"id":149,"image_id":31,"category_id":12},{"segmentation":[[35,7,56,7,56,38,35,38]],"area":651,"bbox":[35,7,21,31],"iscrowd":0,"id":150,"image_id":31,"category_id":2},{"segmentation":[[61,8,82,8,82,40,61,40]],"area":672,"bbox":[61,8,21,32],"iscrowd":0,"id":151,"image_id":31,"category_id":1},{"segmentation":[[85,13,106,13,106,39,85,39]],"area":546,"bbox":[85,13,21,26],"iscrowd":0,"id":152,"image_id":31,"category_id":19},{"segmentation":[[108,6,136,6,136,38,108,38]],"area":896,"bbox":[108,6,28,32],"iscrowd":0,"id":153,"image_id":31,"category_id":16},{"segmentation":[[137,10,175,10,175,42,137,42]],"area":1216,"bbox":[137,10,38,32],"iscrowd":0,"id":154,"image_id":31,"category_id":15},{"segmentation":[[7,11,19,11,19,49,7,49]],"area":456,"bbox":[7,11,12,38],"iscrowd":0,"id":155,"image_id":32,"category_id":40},{"segmentation":[[25,9,47,9,47,43,25,43]],"area":748,"bbox":[25,9,22,34],"iscrowd":0,"id":156,"image_id":32,"category_id":26},{"segmentation":[[51,15,72,15,72,40,51,40]],"area":525,"bbox":[51,15,21,25],"iscrowd":0,"id":157,"image_id":32,"category_id":11},{"segmentation":[[72,16,94,16,94,50,72,50]],"area":748,"bbox":[72,16,22,34],"iscrowd":0,"id":158,"image_id":32,"category_id":24},{"segmentation":[[12,12,42,12,42,44,12,44]],"area":960,"bbox":[12,12,30,32],"iscrowd":0,"id":159,"image_id":33,"category_id":30},{"segmentation":[[44,14,78,14,78,38,44,38]],"area":816,"bbox":[44,14,34,24],"iscrowd":0,"id":160,"image_id":33,"category_id":29},{"segmentation":[[80,7,99,7,99,39,80,39]],"area":608,"bbox":[80,7,19,32],"iscrowd":0,"id":161,"image_id":33,"category_id":32},{"segmentation":[[101,17,123,17,123,50,101,50]],"area":726,"bbox":[101,17,22,33],"iscrowd":0,"id":162,"image_id":33,"category_id":26},{"segmentation":[[11,1,40,1,40,37,11,37]],"area":1044,"bbox":[11,1,29,36],"iscrowd":0,"id":163,"image_id":34,"category_id":33},{"segmentation":[[43,11,64,11,64,44,43,44]],"area":693,"bbox":[43,11,21,33],"iscrowd":0,"id":164,"image_id":34,"category_id":1},{"segmentation":[[64,4,90,4,90,36,64,36]],"area":832,"bbox":[64,4,26,32],"iscrowd":0,"id":165,"image_id":34,"category_id":25},{"segmentation":[[95,11,118,11,118,44,95,44]],"area":759,"bbox":[95,11,23,33],"iscrowd":0,"id":166,"image_id":34,"category_id":10},{"segmentation":[[121,12,147,12,147,44,121,44]],"area":832,"bbox":[121,12,26,32],"iscrowd":0,"id":167,"image_id":34,"category_id":14},{"segmentation":[[8,8,38,8,38,40,8,40]],"area":960,"bbox":[8,8,30,32],"iscrowd":0,"id":168,"image_id":35,"category_id":9},{"segmentation":[[44,3,69,3,69,37,44,37]],"area":850,"bbox":[44,3,25,34],"iscrowd":0,"id":169,"image_id":35,"category_id":27},{"segmentation":[[72,6,96,6,96,39,72,39]],"area":792,"bbox":[72,6,24,33],"iscrowd":0,"id":170,"image_id":35,"category_id":18},{"segmentation":[[98,10,120,10,120,42,98,42]],"area":704,"bbox":[98,10,22,32],"iscrowd":0,"id":171,"image_id":35,"category_id":5},{"segmentation":[[124,5,146,5,146,39,124,39]],"area":748,"bbox":[124,5,22,34],"iscrowd":0,"id":172,"image_id":35,"category_id":39},{"segmentation":[[148,4,170,4,170,36,148,36]],"area":704,"bbox":[148,4,22,32],"iscrowd":0,"id":173,"image_id":35,"category_id":3},{"segmentation":[[9,1,37,1,37,33,9,33]],"area":896,"bbox":[9,1,28,32],"iscrowd":0,"id":174,"image_id":36,"category_id":9},{"segmentation":[[44,9,67,9,67,41,44,41]],"area":736,"bbox":[44,9,23,32],"iscrowd":0,"id":175,"image_id":36,"category_id":31},{"segmentation":[[71,8,92,8,92,41,71,41]],"area":693,"bbox":[71,8,21,33],"iscrowd":0,"id":176,"image_id":36,"category_id":37},{"segmentation":[[93,7,115,7,115,39,93,39]],"area":704,"bbox":[93,7,22,32],"iscrowd":0,"id":177,"image_id":36,"category_id":3},{"segmentation":[[13,11,34,11,34,45,13,45]],"area":714,"bbox":[13,11,21,34],"iscrowd":0,"id":178,"image_id":37,"category_id":34},{"segmentation":[[33,8,72,8,72,40,33,40]],"area":1248,"bbox":[33,8,39,32],"iscrowd":0,"id":179,"image_id":37,"category_id":15},{"segmentation":[[74,10,90,10,90,40,74,40]],"area":480,"bbox":[74,10,16,30],"iscrowd":0,"id":180,"image_id":37,"category_id":7},{"segmentation":[[93,6,120,6,120,38,93,38]],"area":864,"bbox":[93,6,27,32],"iscrowd":0,"id":181,"image_id":37,"category_id":13},{"segmentation":[[125,3,150,3,150,35,125,35]],"area":800,"bbox":[125,3,25,32],"iscrowd":0,"id":182,"image_id":37,"category_id":27},{"segmentation":[[11,8,39,8,39,40,11,40]],"area":896,"bbox":[11,8,28,32],"iscrowd":0,"id":183,"image_id":38,"category_id":13},{"segmentation":[[40,8,66,8,66,41,40,41]],"area":858,"bbox":[40,8,26,33],"iscrowd":0,"id":184,"image_id":38,"category_id":16},{"segmentation":[[70,6,99,6,99,43,70,43]],"area":1073,"bbox":[70,6,29,37],"iscrowd":0,"id":185,"image_id":38,"category_id":33},{"segmentation":[[103,19,137,19,137,45,103,45]],"area":884,"bbox":[103,19,34,26],"iscrowd":0,"id":186,"image_id":38,"category_id":29},{"segmentation":[[139,6,164,6,164,38,139,38]],"area":800,"bbox":[139,6,25,32],"iscrowd":0,"id":187,"image_id":38,"category_id":27},{"segmentation":[[167,6,188,6,188,39,167,39]],"area":693,"bbox":[167,6,21,33],"iscrowd":0,"id":188,"image_id":38,"category_id":39},{"segmentation":[[13,6,37,6,37,38,13,38]],"area":768,"bbox":[13,6,24,32],"iscrowd":0,"id":189,"image_id":39,"category_id":17},{"segmentation":[[40,11,76,11,76,47,40,47]],"area":1296,"bbox":[40,11,36,36],"iscrowd":0,"id":190,"image_id":39,"category_id":23},{"segmentation":[[76,13,86,13,86,50,76,50]],"area":370,"bbox":[76,13,10,37],"iscrowd":0,"id":191,"image_id":39,"category_id":40},{"segmentation":[[89,7,117,7,117,39,89,39]],"area":896,"bbox":[89,7,28,32],"iscrowd":0,"id":192,"image_id":39,"category_id":9},{"segmentation":[[123,8,145,8,145,41,123,41]],"area":726,"bbox":[123,8,22,33],"iscrowd":0,"id":193,"image_id":39,"category_id":3},{"segmentation":[[149,6,171,6,171,39,149,39]],"area":726,"bbox":[149,6,22,33],"iscrowd":0,"id":194,"image_id":39,"category_id":39},{"segmentation":[[11,14,31,14,31,38,11,38]],"area":480,"bbox":[11,14,20,24],"iscrowd":0,"id":195,"image_id":40,"category_id":12},{"segmentation":[[35,12,56,12,56,44,35,44]],"area":672,"bbox":[35,12,21,32],"iscrowd":0,"id":196,"image_id":40,"category_id":4},{"segmentation":[[56,6,72,6,72,36,56,36]],"area":480,"bbox":[56,6,16,30],"iscrowd":0,"id":197,"image_id":40,"category_id":7},{"segmentation":[[74,3,113,3,113,34,74,34]],"area":1209,"bbox":[74,3,39,31],"iscrowd":0,"id":198,"image_id":40,"category_id":15},{"segmentation":[[12,14,48,14,48,50,12,50]],"area":1296,"bbox":[12,14,36,36],"iscrowd":0,"id":199,"image_id":41,"category_id":23},{"segmentation":[[51,0,73,0,73,32,51,32]],"area":704,"bbox":[51,0,22,32],"iscrowd":0,"id":200,"image_id":41,"category_id":3},{"segmentation":[[76,9,98,9,98,40,76,40]],"area":682,"bbox":[76,9,22,31],"iscrowd":0,"id":201,"image_id":41,"category_id":2},{"segmentation":[[101,15,121,15,121,41,101,41]],"area":520,"bbox":[101,15,20,26],"iscrowd":0,"id":202,"image_id":41,"category_id":12},{"segmentation":[[125,9,147,9,147,34,125,34]],"area":550,"bbox":[125,9,22,25],"iscrowd":0,"id":203,"image_id":41,"category_id":19},{"segmentation":[[148,10,187,10,187,42,148,42]],"area":1248,"bbox":[148,10,39,32],"iscrowd":0,"id":204,"image_id":41,"category_id":15},{"segmentation":[[13,12,33,12,33,44,13,44]],"area":640,"bbox":[13,12,20,32],"iscrowd":0,"id":205,"image_id":42,"category_id":32},{"segmentation":[[35,11,54,11,54,42,35,42]],"area":589,"bbox":[35,11,19,31],"iscrowd":0,"id":206,"image_id":42,"category_id":22},{"segmentation":[[58,19,84,19,84,35,58,35]],"area":416,"bbox":[58,19,26,16],"iscrowd":0,"id":207,"image_id":42,"category_id":35},{"segmentation":[[85,17,107,17,107,42,85,42]],"area":550,"bbox":[85,17,22,25],"iscrowd":0,"id":208,"image_id":42,"category_id":19},{"segmentation":[[13,9,33,9,33,40,13,40]],"area":620,"bbox":[13,9,20,31],"iscrowd":0,"id":209,"image_id":43,"category_id":32},{"segmentation":[[36,14,72,14,72,50,36,50]],"area":1296,"bbox":[36,14,36,36],"iscrowd":0,"id":210,"image_id":43,"category_id":23},{"segmentation":[[73,4,96,4,96,34,73,34]],"area":690,"bbox":[73,4,23,30],"iscrowd":0,"id":211,"image_id":43,"category_id":2},{"segmentation":[[100,10,122,10,122,42,100,42]],"area":704,"bbox":[100,10,22,32],"iscrowd":0,"id":212,"image_id":43,"category_id":5},{"segmentation":[[125,3,147,3,147,34,125,34]],"area":682,"bbox":[125,3,22,31],"iscrowd":0,"id":213,"image_id":43,"category_id":5},{"segmentation":[[12,12,37,12,37,43,12,43]],"area":775,"bbox":[12,12,25,31],"iscrowd":0,"id":214,"image_id":44,"category_id":18},{"segmentation":[[39,2,61,2,61,34,39,34]],"area":704,"bbox":[39,2,22,32],"iscrowd":0,"id":215,"image_id":44,"category_id":5},{"segmentation":[[64,8,86,8,86,41,64,41]],"area":726,"bbox":[64,8,22,33],"iscrowd":0,"id":216,"image_id":44,"category_id":3},{"segmentation":[[90,4,110,4,110,36,90,36]],"area":640,"bbox":[90,4,20,32],"iscrowd":0,"id":217,"image_id":44,"category_id":32},{"segmentation":[[111,8,133,8,133,41,111,41]],"area":726,"bbox":[111,8,22,33],"iscrowd":0,"id":218,"image_id":44,"category_id":10},{"segmentation":[[136,11,157,11,157,45,136,45]],"area":714,"bbox":[136,11,21,34],"iscrowd":0,"id":219,"image_id":44,"category_id":1},{"segmentation":[[11,19,33,19,33,50,11,50]],"area":682,"bbox":[11,19,22,31],"iscrowd":0,"id":220,"image_id":45,"category_id":24},{"segmentation":[[37,11,58,11,58,44,37,44]],"area":693,"bbox":[37,11,21,33],"iscrowd":0,"id":221,"image_id":45,"category_id":36},{"segmentation":[[60,8,82,8,82,40,60,40]],"area":704,"bbox":[60,8,22,32],"iscrowd":0,"id":222,"image_id":45,"category_id":3},{"segmentation":[[84,1,107,1,107,33,84,33]],"area":736,"bbox":[84,1,23,32],"iscrowd":0,"id":223,"image_id":45,"category_id":2},{"segmentation":[[111,10,133,10,133,42,111,42]],"area":704,"bbox":[111,10,22,32],"iscrowd":0,"id":224,"image_id":45,"category_id":5},{"segmentation":[[12,10,34,10,34,43,12,43]],"area":726,"bbox":[12,10,22,33],"iscrowd":0,"id":225,"image_id":46,"category_id":5},{"segmentation":[[36,9,51,9,51,40,36,40]],"area":465,"bbox":[36,9,15,31],"iscrowd":0,"id":226,"image_id":46,"category_id":7},{"segmentation":[[56,15,76,15,76,40,56,40]],"area":500,"bbox":[56,15,20,25],"iscrowd":0,"id":227,"image_id":46,"category_id":38},{"segmentation":[[77,9,103,9,103,40,77,40]],"area":806,"bbox":[77,9,26,31],"iscrowd":0,"id":228,"image_id":46,"category_id":41},{"segmentation":[[107,13,131,13,131,45,107,45]],"area":768,"bbox":[107,13,24,32],"iscrowd":0,"id":229,"image_id":46,"category_id":17},{"segmentation":[[133,8,156,8,156,40,133,40]],"area":736,"bbox":[133,8,23,32],"iscrowd":0,"id":230,"image_id":46,"category_id":5},{"segmentation":[[13,1,31,1,31,32,13,32]],"area":558,"bbox":[13,1,18,31],"iscrowd":0,"id":231,"image_id":47,"category_id":22},{"segmentation":[[31,11,47,11,47,44,31,44]],"area":528,"bbox":[31,11,16,33],"iscrowd":0,"id":232,"image_id":47,"category_id":28},{"segmentation":[[51,0,73,0,73,32,51,32]],"area":704,"bbox":[51,0,22,32],"iscrowd":0,"id":233,"image_id":47,"category_id":5},{"segmentation":[[75,13,98,13,98,44,75,44]],"area":713,"bbox":[75,13,23,31],"iscrowd":0,"id":234,"image_id":47,"category_id":2},{"segmentation":[[13,5,34,5,34,38,13,38]],"area":693,"bbox":[13,5,21,33],"iscrowd":0,"id":235,"image_id":48,"category_id":34},{"segmentation":[[36,14,70,14,70,39,36,39]],"area":850,"bbox":[36,14,34,25],"iscrowd":0,"id":236,"image_id":48,"category_id":29},{"segmentation":[[72,15,93,15,93,41,72,41]],"area":546,"bbox":[72,15,21,26],"iscrowd":0,"id":237,"image_id":48,"category_id":38},{"segmentation":[[95,13,110,13,110,38,95,38]],"area":375,"bbox":[95,13,15,25],"iscrowd":0,"id":238,"image_id":48,"category_id":6},{"segmentation":[[11,2,34,2,34,34,11,34]],"area":736,"bbox":[11,2,23,32],"iscrowd":0,"id":239,"image_id":49,"category_id":2},{"segmentation":[[37,8,67,8,67,45,37,45]],"area":1110,"bbox":[37,8,30,37],"iscrowd":0,"id":240,"image_id":49,"category_id":33},{"segmentation":[[70,4,94,4,94,37,70,37]],"area":792,"bbox":[70,4,24,33],"iscrowd":0,"id":241,"image_id":49,"category_id":17},{"segmentation":[[96,6,117,6,117,38,96,38]],"area":672,"bbox":[96,6,21,32],"iscrowd":0,"id":242,"image_id":49,"category_id":1},{"segmentation":[[120,10,146,10,146,42,120,42]],"area":832,"bbox":[120,10,26,32],"iscrowd":0,"id":243,"image_id":49,"category_id":13},{"segmentation":[[13,19,47,19,47,44,13,44]],"area":850,"bbox":[13,19,34,25],"iscrowd":0,"id":244,"image_id":50,"category_id":29},{"segmentation":[[49,12,74,12,74,44,49,44]],"area":800,"bbox":[49,12,25,32],"iscrowd":0,"id":245,"image_id":50,"category_id":27},{"segmentation":[[74,9,113,9,113,40,74,40]],"area":1209,"bbox":[74,9,39,31],"iscrowd":0,"id":246,"image_id":50,"category_id":15},{"segmentation":[[118,10,140,10,140,43,118,43]],"area":726,"bbox":[118,10,22,33],"iscrowd":0,"id":247,"image_id":50,"category_id":37},{"segmentation":[[10,12,49,12,49,44,10,44]],"area":1248,"bbox":[10,12,39,32],"iscrowd":0,"id":248,"image_id":51,"category_id":15},{"segmentation":[[54,9,68,9,68,35,54,35]],"area":364,"bbox":[54,9,14,26],"iscrowd":0,"id":249,"image_id":51,"category_id":6},{"segmentation":[[68,13,106,13,106,44,68,44]],"area":1178,"bbox":[68,13,38,31],"iscrowd":0,"id":250,"image_id":51,"category_id":15},{"segmentation":[[110,8,139,8,139,45,110,45]],"area":1073,"bbox":[110,8,29,37],"iscrowd":0,"id":251,"image_id":51,"category_id":33},{"segmentation":[[13,5,33,5,33,37,13,37]],"area":640,"bbox":[13,5,20,32],"iscrowd":0,"id":252,"image_id":52,"category_id":32},{"segmentation":[[34,6,49,6,49,40,34,40]],"area":510,"bbox":[34,6,15,34],"iscrowd":0,"id":253,"image_id":52,"category_id":28},{"segmentation":[[54,8,79,8,79,40,54,40]],"area":800,"bbox":[54,8,25,32],"iscrowd":0,"id":254,"image_id":52,"category_id":20},{"segmentation":[[81,6,101,6,101,39,81,39]],"area":660,"bbox":[81,6,20,33],"iscrowd":0,"id":255,"image_id":52,"category_id":32},{"segmentation":[[103,6,125,6,125,38,103,38]],"area":704,"bbox":[103,6,22,32],"iscrowd":0,"id":256,"image_id":52,"category_id":5},{"segmentation":[[11,13,33,13,33,46,11,46]],"area":726,"bbox":[11,13,22,33],"iscrowd":0,"id":257,"image_id":53,"category_id":24},{"segmentation":[[37,12,52,12,52,39,37,39]],"area":405,"bbox":[37,12,15,27],"iscrowd":0,"id":258,"image_id":53,"category_id":6},{"segmentation":[[54,9,78,9,78,40,54,40]],"area":744,"bbox":[54,9,24,31],"iscrowd":0,"id":259,"image_id":53,"category_id":27},{"segmentation":[[80,3,106,3,106,34,80,34]],"area":806,"bbox":[80,3,26,31],"iscrowd":0,"id":260,"image_id":53,"category_id":41},{"segmentation":[[107,9,147,9,147,40,107,40]],"area":1240,"bbox":[107,9,40,31],"iscrowd":0,"id":261,"image_id":53,"category_id":15},{"segmentation":[[150,23,179,23,179,37,150,37]],"area":406,"bbox":[150,23,29,14],"iscrowd":0,"id":262,"image_id":53,"category_id":35},{"segmentation":[[13,12,33,12,33,44,13,44]],"area":640,"bbox":[13,12,20,32],"iscrowd":0,"id":263,"image_id":54,"category_id":34},{"segmentation":[[34,12,62,12,62,44,34,44]],"area":896,"bbox":[34,12,28,32],"iscrowd":0,"id":264,"image_id":54,"category_id":13},{"segmentation":[[66,8,92,8,92,40,66,40]],"area":832,"bbox":[66,8,26,32],"iscrowd":0,"id":265,"image_id":54,"category_id":27},{"segmentation":[[93,5,114,5,114,37,93,37]],"area":672,"bbox":[93,5,21,32],"iscrowd":0,"id":266,"image_id":54,"category_id":4},{"segmentation":[[115,10,138,10,138,42,115,42]],"area":736,"bbox":[115,10,23,32],"iscrowd":0,"id":267,"image_id":54,"category_id":2},{"segmentation":[[143,15,165,15,165,41,143,41]],"area":572,"bbox":[143,15,22,26],"iscrowd":0,"id":268,"image_id":54,"category_id":11},{"segmentation":[[13,18,33,18,33,42,13,42]],"area":480,"bbox":[13,18,20,24],"iscrowd":0,"id":269,"image_id":55,"category_id":38},{"segmentation":[[33,6,49,6,49,38,33,38]],"area":512,"bbox":[33,6,16,32],"iscrowd":0,"id":270,"image_id":55,"category_id":28},{"segmentation":[[53,11,75,11,75,43,53,43]],"area":704,"bbox":[53,11,22,32],"iscrowd":0,"id":271,"image_id":55,"category_id":37},{"segmentation":[[75,8,91,8,91,38,75,38]],"area":480,"bbox":[75,8,16,30],"iscrowd":0,"id":272,"image_id":55,"category_id":7},{"segmentation":[[13,9,37,9,37,41,13,41]],"area":768,"bbox":[13,9,24,32],"iscrowd":0,"id":273,"image_id":56,"category_id":17},{"segmentation":[[37,5,53,5,53,39,37,39]],"area":544,"bbox":[37,5,16,34],"iscrowd":0,"id":274,"image_id":56,"category_id":28},{"segmentation":[[58,1,78,1,78,32,58,32]],"area":620,"bbox":[58,1,20,31],"iscrowd":0,"id":275,"image_id":56,"category_id":4},{"segmentation":[[81,9,108,9,108,41,81,41]],"area":864,"bbox":[81,9,27,32],"iscrowd":0,"id":276,"image_id":56,"category_id":14},{"segmentation":[[108,10,146,10,146,42,108,42]],"area":1216,"bbox":[108,10,38,32],"iscrowd":0,"id":277,"image_id":56,"category_id":15},{"segmentation":[[13,7,38,7,38,38,13,38]],"area":775,"bbox":[13,7,25,31],"iscrowd":0,"id":278,"image_id":57,"category_id":20},{"segmentation":[[36,3,63,3,63,35,36,35]],"area":864,"bbox":[36,3,27,32],"iscrowd":0,"id":279,"image_id":57,"category_id":25},{"segmentation":[[65,6,91,6,91,39,65,39]],"area":858,"bbox":[65,6,26,33],"iscrowd":0,"id":280,"image_id":57,"category_id":25},{"segmentation":[[96,2,125,2,125,41,96,41]],"area":1131,"bbox":[96,2,29,39],"iscrowd":0,"id":281,"image_id":57,"category_id":33},{"segmentation":[[11,17,35,17,35,50,11,50]],"area":792,"bbox":[11,17,24,33],"iscrowd":0,"id":282,"image_id":58,"category_id":26},{"segmentation":[[37,9,56,9,56,41,37,41]],"area":608,"bbox":[37,9,19,32],"iscrowd":0,"id":283,"image_id":58,"category_id":22},{"segmentation":[[58,10,83,10,83,42,58,42]],"area":800,"bbox":[58,10,25,32],"iscrowd":0,"id":284,"image_id":58,"category_id":27},{"segmentation":[[86,16,120,16,120,43,86,43]],"area":918,"bbox":[86,16,34,27],"iscrowd":0,"id":285,"image_id":58,"category_id":29},{"segmentation":[[122,9,141,9,141,41,122,41]],"area":608,"bbox":[122,9,19,32],"iscrowd":0,"id":286,"image_id":58,"category_id":22},{"segmentation":[[141,14,156,14,156,45,141,45]],"area":465,"bbox":[141,14,15,31],"iscrowd":0,"id":287,"image_id":58,"category_id":7},{"segmentation":[[13,15,28,15,28,39,13,39]],"area":360,"bbox":[13,15,15,24],"iscrowd":0,"id":288,"image_id":59,"category_id":6},{"segmentation":[[30,13,50,13,50,38,30,38]],"area":500,"bbox":[30,13,20,25],"iscrowd":0,"id":289,"image_id":59,"category_id":11},{"segmentation":[[52,9,77,9,77,42,52,42]],"area":825,"bbox":[52,9,25,33],"iscrowd":0,"id":290,"image_id":59,"category_id":31},{"segmentation":[[77,8,106,8,106,40,77,40]],"area":928,"bbox":[77,8,29,32],"iscrowd":0,"id":291,"image_id":59,"category_id":13},{"segmentation":[[10,0,26,0,26,32,10,32]],"area":512,"bbox":[10,0,16,32],"iscrowd":0,"id":292,"image_id":60,"category_id":28},{"segmentation":[[31,11,49,11,49,44,31,44]],"area":594,"bbox":[31,11,18,33],"iscrowd":0,"id":293,"image_id":60,"category_id":22},{"segmentation":[[52,11,72,11,72,43,52,43]],"area":640,"bbox":[52,11,20,32],"iscrowd":0,"id":294,"image_id":60,"category_id":1},{"segmentation":[[76,10,103,10,103,42,76,42]],"area":864,"bbox":[76,10,27,32],"iscrowd":0,"id":295,"image_id":60,"category_id":14},{"segmentation":[[104,12,131,12,131,44,104,44]],"area":864,"bbox":[104,12,27,32],"iscrowd":0,"id":296,"image_id":60,"category_id":14},{"segmentation":[[13,8,38,8,38,40,13,40]],"area":800,"bbox":[13,8,25,32],"iscrowd":0,"id":297,"image_id":61,"category_id":20},{"segmentation":[[38,6,65,6,65,39,38,39]],"area":891,"bbox":[38,6,27,33],"iscrowd":0,"id":298,"image_id":61,"category_id":41},{"segmentation":[[65,8,104,8,104,41,65,41]],"area":1287,"bbox":[65,8,39,33],"iscrowd":0,"id":299,"image_id":61,"category_id":15},{"segmentation":[[108,14,145,14,145,51,108,51]],"area":1369,"bbox":[108,14,37,37],"iscrowd":0,"id":300,"image_id":61,"category_id":23},{"segmentation":[[147,8,184,8,184,45,147,45]],"area":1369,"bbox":[147,8,37,37],"iscrowd":0,"id":301,"image_id":61,"category_id":23},{"segmentation":[[12,9,34,9,34,43,12,43]],"area":748,"bbox":[12,9,22,34],"iscrowd":0,"id":302,"image_id":62,"category_id":39},{"segmentation":[[35,19,57,19,57,50,35,50]],"area":682,"bbox":[35,19,22,31],"iscrowd":0,"id":303,"image_id":62,"category_id":24},{"segmentation":[[61,4,85,4,85,36,61,36]],"area":768,"bbox":[61,4,24,32],"iscrowd":0,"id":304,"image_id":62,"category_id":27},{"segmentation":[[87,8,116,8,116,45,87,45]],"area":1073,"bbox":[87,8,29,37],"iscrowd":0,"id":305,"image_id":62,"category_id":33},{"segmentation":[[118,7,145,7,145,38,118,38]],"area":837,"bbox":[118,7,27,31],"iscrowd":0,"id":306,"image_id":62,"category_id":41},{"segmentation":[[11,18,33,18,33,50,11,50]],"area":704,"bbox":[11,18,22,32],"iscrowd":0,"id":307,"image_id":63,"category_id":24},{"segmentation":[[36,12,57,12,57,45,36,45]],"area":693,"bbox":[36,12,21,33],"iscrowd":0,"id":308,"image_id":63,"category_id":1},{"segmentation":[[61,14,81,14,81,38,61,38]],"area":480,"bbox":[61,14,20,24],"iscrowd":0,"id":309,"image_id":63,"category_id":11},{"segmentation":[[84,7,108,7,108,39,84,39]],"area":768,"bbox":[84,7,24,32],"iscrowd":0,"id":310,"image_id":63,"category_id":18},{"segmentation":[[109,7,131,7,131,41,109,41]],"area":748,"bbox":[109,7,22,34],"iscrowd":0,"id":311,"image_id":63,"category_id":24},{"segmentation":[[135,8,165,8,165,41,135,41]],"area":990,"bbox":[135,8,30,33],"iscrowd":0,"id":312,"image_id":63,"category_id":30},{"segmentation":[[10,3,26,3,26,36,10,36]],"area":528,"bbox":[10,3,16,33],"iscrowd":0,"id":313,"image_id":64,"category_id":28},{"segmentation":[[25,11,37,11,37,49,25,49]],"area":456,"bbox":[25,11,12,38],"iscrowd":0,"id":314,"image_id":64,"category_id":40},{"segmentation":[[45,7,65,7,65,40,45,40]],"area":660,"bbox":[45,7,20,33],"iscrowd":0,"id":315,"image_id":64,"category_id":36},{"segmentation":[[69,22,96,22,96,37,69,37]],"area":405,"bbox":[69,22,27,15],"iscrowd":0,"id":316,"image_id":64,"category_id":35},{"segmentation":[[13,11,33,11,33,44,13,44]],"area":660,"bbox":[13,11,20,33],"iscrowd":0,"id":317,"image_id":65,"category_id":34},{"segmentation":[[34,17,57,17,57,42,34,42]],"area":575,"bbox":[34,17,23,25],"iscrowd":0,"id":318,"image_id":65,"category_id":19},{"segmentation":[[60,10,97,10,97,47,60,47]],"area":1369,"bbox":[60,10,37,37],"iscrowd":0,"id":319,"image_id":65,"category_id":23},{"segmentation":[[99,12,119,12,119,46,99,46]],"area":680,"bbox":[99,12,20,34],"iscrowd":0,"id":320,"image_id":65,"category_id":1},{"segmentation":[[124,8,143,8,143,41,124,41]],"area":627,"bbox":[124,8,19,33],"iscrowd":0,"id":321,"image_id":65,"category_id":22},{"segmentation":[[11,7,37,7,37,40,11,40]],"area":858,"bbox":[11,7,26,33],"iscrowd":0,"id":322,"image_id":66,"category_id":16},{"segmentation":[[42,21,71,21,71,36,42,36]],"area":435,"bbox":[42,21,29,15],"iscrowd":0,"id":323,"image_id":66,"category_id":35},{"segmentation":[[68,3,98,3,98,34,68,34]],"area":930,"bbox":[68,3,30,31],"iscrowd":0,"id":324,"image_id":66,"category_id":9},{"segmentation":[[103,12,123,12,123,44,103,44]],"area":640,"bbox":[103,12,20,32],"iscrowd":0,"id":325,"image_id":66,"category_id":34},{"segmentation":[[124,14,146,14,146,48,124,48]],"area":748,"bbox":[124,14,22,34],"iscrowd":0,"id":326,"image_id":66,"category_id":24},{"segmentation":[[150,2,171,2,171,35,150,35]],"area":693,"bbox":[150,2,21,33],"iscrowd":0,"id":327,"image_id":66,"category_id":34},{"segmentation":[[13,12,34,12,34,44,13,44]],"area":672,"bbox":[13,12,21,32],"iscrowd":0,"id":328,"image_id":67,"category_id":22},{"segmentation":[[34,11,56,11,56,45,34,45]],"area":748,"bbox":[34,11,22,34],"iscrowd":0,"id":329,"image_id":67,"category_id":25},{"segmentation":[[63,1,84,1,84,33,63,33]],"area":672,"bbox":[63,1,21,32],"iscrowd":0,"id":330,"image_id":67,"category_id":37},{"segmentation":[[86,4,105,4,105,35,86,35]],"area":589,"bbox":[86,4,19,31],"iscrowd":0,"id":331,"image_id":67,"category_id":22},{"segmentation":[[106,2,126,2,126,34,106,34]],"area":640,"bbox":[106,2,20,32],"iscrowd":0,"id":332,"image_id":67,"category_id":22},{"segmentation":[[7,3,20,3,20,43,7,43]],"area":520,"bbox":[7,3,13,40],"iscrowd":0,"id":333,"image_id":68,"category_id":40},{"segmentation":[[26,10,47,10,47,43,26,43]],"area":693,"bbox":[26,10,21,33],"iscrowd":0,"id":334,"image_id":68,"category_id":10},{"segmentation":[[51,6,71,6,71,39,51,39]],"area":660,"bbox":[51,6,20,33],"iscrowd":0,"id":335,"image_id":68,"category_id":32},{"segmentation":[[73,13,94,13,94,38,73,38]],"area":525,"bbox":[73,13,21,25],"iscrowd":0,"id":336,"image_id":68,"category_id":38},{"segmentation":[[95,12,121,12,121,44,95,44]],"area":832,"bbox":[95,12,26,32],"iscrowd":0,"id":337,"image_id":68,"category_id":41},{"segmentation":[[125,11,144,11,144,42,125,42]],"area":589,"bbox":[125,11,19,31],"iscrowd":0,"id":338,"image_id":68,"category_id":22},{"segmentation":[[11,7,38,7,38,39,11,39]],"area":864,"bbox":[11,7,27,32],"iscrowd":0,"id":339,"image_id":69,"category_id":16},{"segmentation":[[42,7,67,7,67,39,42,39]],"area":800,"bbox":[42,7,25,32],"iscrowd":0,"id":340,"image_id":69,"category_id":31},{"segmentation":[[69,9,83,9,83,35,69,35]],"area":364,"bbox":[69,9,14,26],"iscrowd":0,"id":341,"image_id":69,"category_id":6},{"segmentation":[[84,12,113,12,113,49,84,49]],"area":1073,"bbox":[84,12,29,37],"iscrowd":0,"id":342,"image_id":69,"category_id":33},{"segmentation":[[12,7,33,7,33,39,12,39]],"area":672,"bbox":[12,7,21,32],"iscrowd":0,"id":343,"image_id":70,"category_id":1},{"segmentation":[[37,10,62,10,62,42,37,42]],"area":800,"bbox":[37,10,25,32],"iscrowd":0,"id":344,"image_id":70,"category_id":17},{"segmentation":[[64,21,91,21,91,38,64,38]],"area":459,"bbox":[64,21,27,17],"iscrowd":0,"id":345,"image_id":70,"category_id":35},{"segmentation":[[94,10,114,10,114,35,94,35]],"area":500,"bbox":[94,10,20,25],"iscrowd":0,"id":346,"image_id":70,"category_id":11},{"segmentation":[[116,13,141,13,141,45,116,45]],"area":800,"bbox":[116,13,25,32],"iscrowd":0,"id":347,"image_id":70,"category_id":17},{"segmentation":[[144,12,169,12,169,45,144,45]],"area":825,"bbox":[144,12,25,33],"iscrowd":0,"id":348,"image_id":70,"category_id":27},{"segmentation":[[12,6,31,6,31,38,12,38]],"area":608,"bbox":[12,6,19,32],"iscrowd":0,"id":349,"image_id":71,"category_id":22},{"segmentation":[[34,15,61,15,61,31,34,31]],"area":432,"bbox":[34,15,27,16],"iscrowd":0,"id":350,"image_id":71,"category_id":35},{"segmentation":[[62,12,89,12,89,44,62,44]],"area":864,"bbox":[62,12,27,32],"iscrowd":0,"id":351,"image_id":71,"category_id":13},{"segmentation":[[91,9,107,9,107,43,91,43]],"area":544,"bbox":[91,9,16,34],"iscrowd":0,"id":352,"image_id":71,"category_id":28},{"segmentation":[[108,6,150,6,150,38,108,38]],"area":1344,"bbox":[108,6,42,32],"iscrowd":0,"id":353,"image_id":71,"category_id":15},{"segmentation":[[13,19,34,19,34,43,13,43]],"area":504,"bbox":[13,19,21,24],"iscrowd":0,"id":354,"image_id":72,"category_id":11},{"segmentation":[[33,6,60,6,60,39,33,39]],"area":891,"bbox":[33,6,27,33],"iscrowd":0,"id":355,"image_id":72,"category_id":41},{"segmentation":[[64,6,89,6,89,39,64,39]],"area":825,"bbox":[64,6,25,33],"iscrowd":0,"id":356,"image_id":72,"category_id":31},{"segmentation":[[91,17,111,17,111,42,91,42]],"area":500,"bbox":[91,17,20,25],"iscrowd":0,"id":357,"image_id":72,"category_id":38},{"segmentation":[[113,2,150,2,150,39,113,39]],"area":1369,"bbox":[113,2,37,37],"iscrowd":0,"id":358,"image_id":72,"category_id":23},{"segmentation":[[151,1,177,1,177,35,151,35]],"area":884,"bbox":[151,1,26,34],"iscrowd":0,"id":359,"image_id":72,"category_id":16},{"segmentation":[[11,7,35,7,35,39,11,39]],"area":768,"bbox":[11,7,24,32],"iscrowd":0,"id":360,"image_id":73,"category_id":5},{"segmentation":[[37,9,59,9,59,43,37,43]],"area":748,"bbox":[37,9,22,34],"iscrowd":0,"id":361,"image_id":73,"category_id":10},{"segmentation":[[62,12,84,12,84,44,62,44]],"area":704,"bbox":[62,12,22,32],"iscrowd":0,"id":362,"image_id":73,"category_id":39},{"segmentation":[[85,4,110,4,110,37,85,37]],"area":825,"bbox":[85,4,25,33],"iscrowd":0,"id":363,"image_id":73,"category_id":20},{"segmentation":[[10,5,26,5,26,39,10,39]],"area":544,"bbox":[10,5,16,34],"iscrowd":0,"id":364,"image_id":74,"category_id":28},{"segmentation":[[27,10,55,10,55,42,27,42]],"area":896,"bbox":[27,10,28,32],"iscrowd":0,"id":365,"image_id":74,"category_id":9},{"segmentation":[[59,12,98,12,98,44,59,44]],"area":1248,"bbox":[59,12,39,32],"iscrowd":0,"id":366,"image_id":74,"category_id":15},{"segmentation":[[103,1,123,1,123,32,103,32]],"area":620,"bbox":[103,1,20,31],"iscrowd":0,"id":367,"image_id":74,"category_id":36},{"segmentation":[[124,7,141,7,141,38,124,38]],"area":527,"bbox":[124,7,17,31],"iscrowd":0,"id":368,"image_id":74,"category_id":7},{"segmentation":[[11,17,33,17,33,50,11,50]],"area":726,"bbox":[11,17,22,33],"iscrowd":0,"id":369,"image_id":75,"category_id":24},{"segmentation":[[36,11,57,11,57,45,36,45]],"area":714,"bbox":[36,11,21,34],"iscrowd":0,"id":370,"image_id":75,"category_id":10},{"segmentation":[[60,8,86,8,86,43,60,43]],"area":910,"bbox":[60,8,26,35],"iscrowd":0,"id":371,"image_id":75,"category_id":13},{"segmentation":[[90,6,115,6,115,38,90,38]],"area":800,"bbox":[90,6,25,32],"iscrowd":0,"id":372,"image_id":75,"category_id":20},{"segmentation":[[117,10,137,10,137,42,117,42]],"area":640,"bbox":[117,10,20,32],"iscrowd":0,"id":373,"image_id":75,"category_id":1},{"segmentation":[[139,13,156,13,156,45,139,45]],"area":544,"bbox":[139,13,17,32],"iscrowd":0,"id":374,"image_id":75,"category_id":7},{"segmentation":[[12,19,33,19,33,45,12,45]],"area":546,"bbox":[12,19,21,26],"iscrowd":0,"id":375,"image_id":76,"category_id":38},{"segmentation":[[34,10,56,10,56,42,34,42]],"area":704,"bbox":[34,10,22,32],"iscrowd":0,"id":376,"image_id":76,"category_id":5},{"segmentation":[[60,7,82,7,82,40,60,40]],"area":726,"bbox":[60,7,22,33],"iscrowd":0,"id":377,"image_id":76,"category_id":5},{"segmentation":[[85,5,106,5,106,38,85,38]],"area":693,"bbox":[85,5,21,33],"iscrowd":0,"id":378,"image_id":76,"category_id":34},{"segmentation":[[108,13,134,13,134,45,108,45]],"area":832,"bbox":[108,13,26,32],"iscrowd":0,"id":379,"image_id":76,"category_id":20},{"segmentation":[[12,10,40,10,40,43,12,43]],"area":924,"bbox":[12,10,28,33],"iscrowd":0,"id":380,"image_id":77,"category_id":14},{"segmentation":[[39,5,54,5,54,38,39,38]],"area":495,"bbox":[39,5,15,33],"iscrowd":0,"id":381,"image_id":77,"category_id":28},{"segmentation":[[58,16,78,16,78,43,58,43]],"area":540,"bbox":[58,16,20,27],"iscrowd":0,"id":382,"image_id":77,"category_id":12},{"segmentation":[[83,18,104,18,104,44,83,44]],"area":546,"bbox":[83,18,21,26],"iscrowd":0,"id":383,"image_id":77,"category_id":38},{"segmentation":[[106,19,121,19,121,44,106,44]],"area":375,"bbox":[106,19,15,25],"iscrowd":0,"id":384,"image_id":77,"category_id":6},{"segmentation":[[11,10,49,10,49,48,11,48]],"area":1444,"bbox":[11,10,38,38],"iscrowd":0,"id":385,"image_id":78,"category_id":23},{"segmentation":[[50,9,88,9,88,46,50,46]],"area":1406,"bbox":[50,9,38,37],"iscrowd":0,"id":386,"image_id":78,"category_id":23},{"segmentation":[[89,11,115,11,115,43,89,43]],"area":832,"bbox":[89,11,26,32],"iscrowd":0,"id":387,"image_id":78,"category_id":16},{"segmentation":[[117,12,146,12,146,45,117,45]],"area":957,"bbox":[117,12,29,33],"iscrowd":0,"id":388,"image_id":78,"category_id":16},{"segmentation":[[13,8,37,8,37,41,13,41]],"area":792,"bbox":[13,8,24,33],"iscrowd":0,"id":389,"image_id":79,"category_id":18},{"segmentation":[[38,8,76,8,76,41,38,41]],"area":1254,"bbox":[38,8,38,33],"iscrowd":0,"id":390,"image_id":79,"category_id":15},{"segmentation":[[80,21,108,21,108,36,80,36]],"area":420,"bbox":[80,21,28,15],"iscrowd":0,"id":391,"image_id":79,"category_id":35},{"segmentation":[[108,6,147,6,147,38,108,38]],"area":1248,"bbox":[108,6,39,32],"iscrowd":0,"id":392,"image_id":79,"category_id":15},{"segmentation":[[149,4,176,4,176,37,149,37]],"area":891,"bbox":[149,4,27,33],"iscrowd":0,"id":393,"image_id":79,"category_id":16},{"segmentation":[[180,3,201,3,201,37,180,37]],"area":714,"bbox":[180,3,21,34],"iscrowd":0,"id":394,"image_id":79,"category_id":1},{"segmentation":[[11,19,34,19,34,50,11,50]],"area":713,"bbox":[11,19,23,31],"iscrowd":0,"id":395,"image_id":80,"category_id":24},{"segmentation":[[36,5,57,5,57,38,36,38]],"area":693,"bbox":[36,5,21,33],"iscrowd":0,"id":396,"image_id":80,"category_id":1},{"segmentation":[[60,8,81,8,81,42,60,42]],"area":714,"bbox":[60,8,21,34],"iscrowd":0,"id":397,"image_id":80,"category_id":34},{"segmentation":[[84,19,104,19,104,45,84,45]],"area":520,"bbox":[84,19,20,26],"iscrowd":0,"id":398,"image_id":80,"category_id":11},{"segmentation":[[107,5,129,5,129,39,107,39]],"area":748,"bbox":[107,5,22,34],"iscrowd":0,"id":399,"image_id":80,"category_id":39},{"segmentation":[[12,7,47,7,47,33,12,33]],"area":910,"bbox":[12,7,35,26],"iscrowd":0,"id":400,"image_id":81,"category_id":29},{"segmentation":[[49,9,69,9,69,43,49,43]],"area":680,"bbox":[49,9,20,34],"iscrowd":0,"id":401,"image_id":81,"category_id":36},{"segmentation":[[73,9,97,9,97,42,73,42]],"area":792,"bbox":[73,9,24,33],"iscrowd":0,"id":402,"image_id":81,"category_id":18},{"segmentation":[[100,9,121,9,121,36,100,36]],"area":567,"bbox":[100,9,21,27],"iscrowd":0,"id":403,"image_id":81,"category_id":11},{"segmentation":[[123,3,148,3,148,37,123,37]],"area":850,"bbox":[123,3,25,34],"iscrowd":0,"id":404,"image_id":81,"category_id":27},{"segmentation":[[150,16,171,16,171,44,150,44]],"area":588,"bbox":[150,16,21,28],"iscrowd":0,"id":405,"image_id":81,"category_id":11},{"segmentation":[[13,5,34,5,34,39,13,39]],"area":714,"bbox":[13,5,21,34],"iscrowd":0,"id":406,"image_id":82,"category_id":34},{"segmentation":[[35,8,60,8,60,41,35,41]],"area":825,"bbox":[35,8,25,33],"iscrowd":0,"id":407,"image_id":82,"category_id":31},{"segmentation":[[62,1,83,1,83,33,62,33]],"area":672,"bbox":[62,1,21,32],"iscrowd":0,"id":408,"image_id":82,"category_id":4},{"segmentation":[[83,10,108,10,108,42,83,42]],"area":800,"bbox":[83,10,25,32],"iscrowd":0,"id":409,"image_id":82,"category_id":8},{"segmentation":[[114,16,135,16,135,43,114,43]],"area":567,"bbox":[114,16,21,27],"iscrowd":0,"id":410,"image_id":82,"category_id":38},{"segmentation":[[12,9,34,9,34,42,12,42]],"area":726,"bbox":[12,9,22,33],"iscrowd":0,"id":411,"image_id":83,"category_id":36},{"segmentation":[[36,8,61,8,61,41,36,41]],"area":825,"bbox":[36,8,25,33],"iscrowd":0,"id":412,"image_id":83,"category_id":27},{"segmentation":[[65,15,85,15,85,41,65,41]],"area":520,"bbox":[65,15,20,26],"iscrowd":0,"id":413,"image_id":83,"category_id":11},{"segmentation":[[88,6,108,6,108,38,88,38]],"area":640,"bbox":[88,6,20,32],"iscrowd":0,"id":414,"image_id":83,"category_id":32},{"segmentation":[[110,6,131,6,131,38,110,38]],"area":672,"bbox":[110,6,21,32],"iscrowd":0,"id":415,"image_id":83,"category_id":1},{"segmentation":[[134,5,159,5,159,39,134,39]],"area":850,"bbox":[134,5,25,34],"iscrowd":0,"id":416,"image_id":83,"category_id":17},{"segmentation":[[10,10,27,10,27,42,10,42]],"area":544,"bbox":[10,10,17,32],"iscrowd":0,"id":417,"image_id":84,"category_id":7},{"segmentation":[[29,8,56,8,56,41,29,41]],"area":891,"bbox":[29,8,27,33],"iscrowd":0,"id":418,"image_id":84,"category_id":13},{"segmentation":[[60,6,90,6,90,40,60,40]],"area":1020,"bbox":[60,6,30,34],"iscrowd":0,"id":419,"image_id":84,"category_id":30},{"segmentation":[[92,7,112,7,112,41,92,41]],"area":680,"bbox":[92,7,20,34],"iscrowd":0,"id":420,"image_id":84,"category_id":34},{"segmentation":[[114,1,137,1,137,34,114,34]],"area":759,"bbox":[114,1,23,33],"iscrowd":0,"id":421,"image_id":84,"category_id":5},{"segmentation":[[8,11,36,11,36,43,8,43]],"area":896,"bbox":[8,11,28,32],"iscrowd":0,"id":422,"image_id":85,"category_id":25},{"segmentation":[[41,12,67,12,67,45,41,45]],"area":858,"bbox":[41,12,26,33],"iscrowd":0,"id":423,"image_id":85,"category_id":27},{"segmentation":[[70,3,90,3,90,36,70,36]],"area":660,"bbox":[70,3,20,33],"iscrowd":0,"id":424,"image_id":85,"category_id":36},{"segmentation":[[93,18,108,18,108,45,93,45]],"area":405,"bbox":[93,18,15,27],"iscrowd":0,"id":425,"image_id":85,"category_id":6},{"segmentation":[[110,9,135,9,135,41,110,41]],"area":800,"bbox":[110,9,25,32],"iscrowd":0,"id":426,"image_id":85,"category_id":31},{"segmentation":[[11,7,34,7,34,41,11,41]],"area":782,"bbox":[11,7,23,34],"iscrowd":0,"id":427,"image_id":86,"category_id":1},{"segmentation":[[35,6,61,6,61,39,35,39]],"area":858,"bbox":[35,6,26,33],"iscrowd":0,"id":428,"image_id":86,"category_id":41},{"segmentation":[[61,8,87,8,87,40,61,40]],"area":832,"bbox":[61,8,26,32],"iscrowd":0,"id":429,"image_id":86,"category_id":8},{"segmentation":[[92,12,118,12,118,45,92,45]],"area":858,"bbox":[92,12,26,33],"iscrowd":0,"id":430,"image_id":86,"category_id":41},{"segmentation":[[117,8,147,8,147,40,117,40]],"area":960,"bbox":[117,8,30,32],"iscrowd":0,"id":431,"image_id":86,"category_id":9},{"segmentation":[[151,17,174,17,174,44,151,44]],"area":621,"bbox":[151,17,23,27],"iscrowd":0,"id":432,"image_id":86,"category_id":19},{"segmentation":[[12,9,35,9,35,43,12,43]],"area":782,"bbox":[12,9,23,34],"iscrowd":0,"id":433,"image_id":87,"category_id":3},{"segmentation":[[38,1,60,1,60,34,38,34]],"area":726,"bbox":[38,1,22,33],"iscrowd":0,"id":434,"image_id":87,"category_id":37},{"segmentation":[[61,10,80,10,80,43,61,43]],"area":627,"bbox":[61,10,19,33],"iscrowd":0,"id":435,"image_id":87,"category_id":22},{"segmentation":[[81,13,97,13,97,38,81,38]],"area":400,"bbox":[81,13,16,25],"iscrowd":0,"id":436,"image_id":87,"category_id":6},{"segmentation":[[13,23,41,23,41,38,13,38]],"area":420,"bbox":[13,23,28,15],"iscrowd":0,"id":437,"image_id":88,"category_id":35},{"segmentation":[[41,17,62,17,62,42,41,42]],"area":525,"bbox":[41,17,21,25],"iscrowd":0,"id":438,"image_id":88,"category_id":12},{"segmentation":[[66,3,87,3,87,36,66,36]],"area":693,"bbox":[66,3,21,33],"iscrowd":0,"id":439,"image_id":88,"category_id":21},{"segmentation":[[89,6,111,6,111,39,89,39]],"area":726,"bbox":[89,6,22,33],"iscrowd":0,"id":440,"image_id":88,"category_id":37},{"segmentation":[[12,8,40,8,40,40,12,40]],"area":896,"bbox":[12,8,28,32],"iscrowd":0,"id":441,"image_id":89,"category_id":14},{"segmentation":[[41,0,64,0,64,32,41,32]],"area":736,"bbox":[41,0,23,32],"iscrowd":0,"id":442,"image_id":89,"category_id":39},{"segmentation":[[66,13,87,13,87,39,66,39]],"area":546,"bbox":[66,13,21,26],"iscrowd":0,"id":443,"image_id":89,"category_id":38},{"segmentation":[[88,1,109,1,109,34,88,34]],"area":693,"bbox":[88,1,21,33],"iscrowd":0,"id":444,"image_id":89,"category_id":36},{"segmentation":[[109,9,139,9,139,41,109,41]],"area":960,"bbox":[109,9,30,32],"iscrowd":0,"id":445,"image_id":89,"category_id":9},{"segmentation":[[140,6,166,6,166,39,140,39]],"area":858,"bbox":[140,6,26,33],"iscrowd":0,"id":446,"image_id":89,"category_id":8},{"segmentation":[[12,8,33,8,33,40,12,40]],"area":672,"bbox":[12,8,21,32],"iscrowd":0,"id":447,"image_id":90,"category_id":1},{"segmentation":[[36,19,57,19,57,50,36,50]],"area":651,"bbox":[36,19,21,31],"iscrowd":0,"id":448,"image_id":90,"category_id":24},{"segmentation":[[60,12,85,12,85,43,60,43]],"area":775,"bbox":[60,12,25,31],"iscrowd":0,"id":449,"image_id":90,"category_id":20},{"segmentation":[[86,17,108,17,108,50,86,50]],"area":726,"bbox":[86,17,22,33],"iscrowd":0,"id":450,"image_id":90,"category_id":24},{"segmentation":[[112,13,127,13,127,38,112,38]],"area":375,"bbox":[112,13,15,25],"iscrowd":0,"id":451,"image_id":90,"category_id":6},{"segmentation":[[129,9,150,9,150,43,129,43]],"area":714,"bbox":[129,9,21,34],"iscrowd":0,"id":452,"image_id":90,"category_id":34},{"segmentation":[[12,6,34,6,34,38,12,38]],"area":704,"bbox":[12,6,22,32],"iscrowd":0,"id":453,"image_id":91,"category_id":3},{"segmentation":[[36,12,64,12,64,50,36,50]],"area":1064,"bbox":[36,12,28,38],"iscrowd":0,"id":454,"image_id":91,"category_id":33},{"segmentation":[[69,14,84,14,84,41,69,41]],"area":405,"bbox":[69,14,15,27],"iscrowd":0,"id":455,"image_id":91,"category_id":6},{"segmentation":[[85,1,122,1,122,38,85,38]],"area":1369,"bbox":[85,1,37,37],"iscrowd":0,"id":456,"image_id":91,"category_id":23},{"segmentation":[[125,19,146,19,146,44,125,44]],"area":525,"bbox":[125,19,21,25],"iscrowd":0,"id":457,"image_id":91,"category_id":38},{"segmentation":[[146,5,169,5,169,40,146,40]],"area":805,"bbox":[146,5,23,35],"iscrowd":0,"id":458,"image_id":91,"category_id":10},{"segmentation":[[8,11,37,11,37,45,8,45]],"area":986,"bbox":[8,11,29,34],"iscrowd":0,"id":459,"image_id":92,"category_id":9},{"segmentation":[[40,7,66,7,66,40,40,40]],"area":858,"bbox":[40,7,26,33],"iscrowd":0,"id":460,"image_id":92,"category_id":8},{"segmentation":[[70,6,110,6,110,38,70,38]],"area":1280,"bbox":[70,6,40,32],"iscrowd":0,"id":461,"image_id":92,"category_id":15},{"segmentation":[[114,12,130,12,130,39,114,39]],"area":432,"bbox":[114,12,16,27],"iscrowd":0,"id":462,"image_id":92,"category_id":6},{"segmentation":[[11,8,38,8,38,40,11,40]],"area":864,"bbox":[11,8,27,32],"iscrowd":0,"id":463,"image_id":93,"category_id":13},{"segmentation":[[42,10,63,10,63,42,42,42]],"area":672,"bbox":[42,10,21,32],"iscrowd":0,"id":464,"image_id":93,"category_id":4},{"segmentation":[[64,12,92,12,92,44,64,44]],"area":896,"bbox":[64,12,28,32],"iscrowd":0,"id":465,"image_id":93,"category_id":13},{"segmentation":[[95,8,116,8,116,40,95,40]],"area":672,"bbox":[95,8,21,32],"iscrowd":0,"id":466,"image_id":93,"category_id":21},{"segmentation":[[117,8,144,8,144,42,117,42]],"area":918,"bbox":[117,8,27,34],"iscrowd":0,"id":467,"image_id":93,"category_id":41},{"segmentation":[[146,13,168,13,168,45,146,45]],"area":704,"bbox":[146,13,22,32],"iscrowd":0,"id":468,"image_id":93,"category_id":21},{"segmentation":[[11,15,33,15,33,40,11,40]],"area":550,"bbox":[11,15,22,25],"iscrowd":0,"id":469,"image_id":94,"category_id":19},{"segmentation":[[35,12,74,12,74,44,35,44]],"area":1248,"bbox":[35,12,39,32],"iscrowd":0,"id":470,"image_id":94,"category_id":15},{"segmentation":[[79,2,100,2,100,35,79,35]],"area":693,"bbox":[79,2,21,33],"iscrowd":0,"id":471,"image_id":94,"category_id":21},{"segmentation":[[102,19,137,19,137,45,102,45]],"area":910,"bbox":[102,19,35,26],"iscrowd":0,"id":472,"image_id":94,"category_id":29},{"segmentation":[[138,7,163,7,163,39,138,39]],"area":800,"bbox":[138,7,25,32],"iscrowd":0,"id":473,"image_id":94,"category_id":20},{"segmentation":[[164,5,190,5,190,40,164,40]],"area":910,"bbox":[164,5,26,35],"iscrowd":0,"id":474,"image_id":94,"category_id":16},{"segmentation":[[11,7,33,7,33,41,11,41]],"area":748,"bbox":[11,7,22,34],"iscrowd":0,"id":475,"image_id":95,"category_id":4},{"segmentation":[[36,3,57,3,57,37,36,37]],"area":714,"bbox":[36,3,21,34],"iscrowd":0,"id":476,"image_id":95,"category_id":3},{"segmentation":[[59,5,82,5,82,40,59,40]],"area":805,"bbox":[59,5,23,35],"iscrowd":0,"id":477,"image_id":95,"category_id":10},{"segmentation":[[84,17,113,17,113,35,84,35]],"area":522,"bbox":[84,17,29,18],"iscrowd":0,"id":478,"image_id":95,"category_id":35},{"segmentation":[[8,3,20,3,20,43,8,43]],"area":480,"bbox":[8,3,12,40],"iscrowd":0,"id":479,"image_id":96,"category_id":40},{"segmentation":[[26,9,47,9,47,43,26,43]],"area":714,"bbox":[26,9,21,34],"iscrowd":0,"id":480,"image_id":96,"category_id":1},{"segmentation":[[48,1,75,1,75,33,48,33]],"area":864,"bbox":[48,1,27,32],"iscrowd":0,"id":481,"image_id":96,"category_id":41},{"segmentation":[[76,1,101,1,101,32,76,32]],"area":775,"bbox":[76,1,25,31],"iscrowd":0,"id":482,"image_id":96,"category_id":8},{"segmentation":[[108,2,129,2,129,35,108,35]],"area":693,"bbox":[108,2,21,33],"iscrowd":0,"id":483,"image_id":96,"category_id":37},{"segmentation":[[129,11,151,11,151,36,129,36]],"area":550,"bbox":[129,11,22,25],"iscrowd":0,"id":484,"image_id":96,"category_id":19},{"segmentation":[[11,6,34,6,34,41,11,41]],"area":805,"bbox":[11,6,23,35],"iscrowd":0,"id":485,"image_id":97,"category_id":10},{"segmentation":[[36,19,55,19,55,45,36,45]],"area":494,"bbox":[36,19,19,26],"iscrowd":0,"id":486,"image_id":97,"category_id":12},{"segmentation":[[58,3,80,3,80,36,58,36]],"area":726,"bbox":[58,3,22,33],"iscrowd":0,"id":487,"image_id":97,"category_id":1},{"segmentation":[[82,9,109,9,109,42,82,42]],"area":891,"bbox":[82,9,27,33],"iscrowd":0,"id":488,"image_id":97,"category_id":13},{"segmentation":[[12,6,37,6,37,39,12,39]],"area":825,"bbox":[12,6,25,33],"iscrowd":0,"id":489,"image_id":98,"category_id":31},{"segmentation":[[38,8,65,8,65,40,38,40]],"area":864,"bbox":[38,8,27,32],"iscrowd":0,"id":490,"image_id":98,"category_id":13},{"segmentation":[[68,9,91,9,91,43,68,43]],"area":782,"bbox":[68,9,23,34],"iscrowd":0,"id":491,"image_id":98,"category_id":24},{"segmentation":[[92,10,130,10,130,43,92,43]],"area":1254,"bbox":[92,10,38,33],"iscrowd":0,"id":492,"image_id":98,"category_id":15},{"segmentation":[[135,6,160,6,160,39,135,39]],"area":825,"bbox":[135,6,25,33],"iscrowd":0,"id":493,"image_id":98,"category_id":18},{"segmentation":[[13,16,33,16,33,42,13,42]],"area":520,"bbox":[13,16,20,26],"iscrowd":0,"id":494,"image_id":99,"category_id":11},{"segmentation":[[36,9,57,9,57,43,36,43]],"area":714,"bbox":[36,9,21,34],"iscrowd":0,"id":495,"image_id":99,"category_id":34},{"segmentation":[[56,6,94,6,94,41,56,41]],"area":1330,"bbox":[56,6,38,35],"iscrowd":0,"id":496,"image_id":99,"category_id":15},{"segmentation":[[100,9,135,9,135,48,100,48]],"area":1365,"bbox":[100,9,35,39],"iscrowd":0,"id":497,"image_id":99,"category_id":23},{"segmentation":[[136,9,153,9,153,40,136,40]],"area":527,"bbox":[136,9,17,31],"iscrowd":0,"id":498,"image_id":99,"category_id":7},{"segmentation":[[11,6,39,6,39,38,11,38]],"area":896,"bbox":[11,6,28,32],"iscrowd":0,"id":499,"image_id":100,"category_id":13},{"segmentation":[[41,7,78,7,78,45,41,45]],"area":1406,"bbox":[41,7,37,38],"iscrowd":0,"id":500,"image_id":100,"category_id":23},{"segmentation":[[81,7,101,7,101,39,81,39]],"area":640,"bbox":[81,7,20,32],"iscrowd":0,"id":501,"image_id":100,"category_id":32},{"segmentation":[[103,17,126,17,126,51,103,51]],"area":782,"bbox":[103,17,23,34],"iscrowd":0,"id":502,"image_id":100,"category_id":24}],"licenses":[{"id":0,"name":"Unknown License","url":""}],"categories":[{"supercategory":"name","id":1,"name":"3"},{"supercategory":"name","id":2,"name":"4"},{"supercategory":"name","id":3,"name":"6"},{"supercategory":"name","id":4,"name":"7"},{"supercategory":"name","id":5,"name":"9"},{"supercategory":"name","id":6,"name":"r"},{"supercategory":"name","id":7,"name":"t"},{"supercategory":"name","id":8,"name":"Y"},{"supercategory":"name","id":9,"name":"V"},{"supercategory":"name","id":10,"name":"d"},{"supercategory":"name","id":11,"name":"u"},{"supercategory":"name","id":12,"name":"a"},{"supercategory":"name","id":13,"name":"G"},{"supercategory":"name","id":14,"name":"D"},{"supercategory":"name","id":15,"name":"W"},{"supercategory":"name","id":16,"name":"X"},{"supercategory":"name","id":17,"name":"H"},{"supercategory":"name","id":18,"name":"U"},{"supercategory":"name","id":19,"name":"e"},{"supercategory":"name","id":20,"name":"R"},{"supercategory":"name","id":21,"name":"P"},{"supercategory":"name","id":22,"name":"F"},{"supercategory":"name","id":23,"name":"@"},{"supercategory":"name","id":24,"name":"g"},{"supercategory":"name","id":25,"name":"T"},{"supercategory":"name","id":26,"name":"q"},{"supercategory":"name","id":27,"name":"K"},{"supercategory":"name","id":28,"name":"f"},{"supercategory":"name","id":29,"name":"m"},{"supercategory":"name","id":30,"name":"M"},{"supercategory":"name","id":31,"name":"N"},{"supercategory":"name","id":32,"name":"L"},{"supercategory":"name","id":33,"name":"Q"},{"supercategory":"name","id":34,"name":"h"},{"supercategory":"name","id":35,"name":"="},{"supercategory":"name","id":36,"name":"k"},{"supercategory":"name","id":37,"name":"E"},{"supercategory":"name","id":38,"name":"n"},{"supercategory":"name","id":39,"name":"b"},{"supercategory":"name","id":40,"name":"J"},{"supercategory":"name","id":41,"name":"Z"}]}